[
  {
    "date_start":621734400000,
    "date_end":622252800000,
    "smoothed_cost_price":1.0504107813,
    "STORE":100,
    "UPC":1660051312
  },
  {
    "date_start":622339200000,
    "date_end":622857600000,
    "smoothed_cost_price":1.0975755219,
    "STORE":93,
    "UPC":1660051312
  },
  {
    "date_start":622944000000,
    "date_end":623462400000,
    "smoothed_cost_price":1.1365553401,
    "STORE":122,
    "UPC":1660051312
  },
  {
    "date_start":623548800000,
    "date_end":624067200000,
    "smoothed_cost_price":1.1228678164,
    "STORE":80,
    "UPC":1660051312
  },
  {
    "date_start":624153600000,
    "date_end":624672000000,
    "smoothed_cost_price":1.1509506153,
    "STORE":18,
    "UPC":1660051312
  },
  {
    "date_start":624758400000,
    "date_end":625276800000,
    "smoothed_cost_price":1.1368332614,
    "STORE":105,
    "UPC":1660051312
  },
  {
    "date_start":625363200000,
    "date_end":625881600000,
    "smoothed_cost_price":1.1694132749,
    "STORE":98,
    "UPC":1660051312
  },
  {
    "date_start":625968000000,
    "date_end":626486400000,
    "smoothed_cost_price":1.1959511724,
    "STORE":130,
    "UPC":1660051312
  },
  {
    "date_start":626572800000,
    "date_end":627091200000,
    "smoothed_cost_price":1.166022778,
    "STORE":121,
    "UPC":1660051312
  },
  {
    "date_start":627177600000,
    "date_end":627696000000,
    "smoothed_cost_price":1.1835459326,
    "STORE":132,
    "UPC":1660051312
  },
  {
    "date_start":627782400000,
    "date_end":628300800000,
    "smoothed_cost_price":1.0556384153,
    "STORE":105,
    "UPC":1660051312
  },
  {
    "date_start":628387200000,
    "date_end":628905600000,
    "smoothed_cost_price":1.0976912724,
    "STORE":32,
    "UPC":1660051312
  },
  {
    "date_start":628992000000,
    "date_end":629510400000,
    "smoothed_cost_price":1.0851544055,
    "STORE":80,
    "UPC":1660051312
  },
  {
    "date_start":629596800000,
    "date_end":630115200000,
    "smoothed_cost_price":1.0470968099,
    "STORE":32,
    "UPC":1660051312
  },
  {
    "date_start":630201600000,
    "date_end":630720000000,
    "smoothed_cost_price":1.0141358455,
    "STORE":121,
    "UPC":1660051312
  },
  {
    "date_start":630806400000,
    "date_end":631324800000,
    "smoothed_cost_price":0.9679596625,
    "STORE":44,
    "UPC":1660051312
  },
  {
    "date_start":631411200000,
    "date_end":631929600000,
    "smoothed_cost_price":0.9502111946,
    "STORE":105,
    "UPC":1660051312
  },
  {
    "date_start":632016000000,
    "date_end":632534400000,
    "smoothed_cost_price":0.9635429962,
    "STORE":111,
    "UPC":1660051312
  },
  {
    "date_start":632620800000,
    "date_end":633139200000,
    "smoothed_cost_price":1.0236070259,
    "STORE":121,
    "UPC":1660051312
  },
  {
    "date_start":633225600000,
    "date_end":633744000000,
    "smoothed_cost_price":1.0575100642,
    "STORE":98,
    "UPC":1660051312
  },
  {
    "date_start":633830400000,
    "date_end":634348800000,
    "smoothed_cost_price":1.0786150235,
    "STORE":44,
    "UPC":1660051312
  },
  {
    "date_start":634435200000,
    "date_end":634953600000,
    "smoothed_cost_price":1.1192451419,
    "STORE":114,
    "UPC":1660051312
  },
  {
    "date_start":635040000000,
    "date_end":635558400000,
    "smoothed_cost_price":1.0970592691,
    "STORE":32,
    "UPC":1660051312
  },
  {
    "date_start":635644800000,
    "date_end":636163200000,
    "smoothed_cost_price":1.1357655399,
    "STORE":109,
    "UPC":1660051312
  },
  {
    "date_start":636249600000,
    "date_end":636768000000,
    "smoothed_cost_price":1.1673158297,
    "STORE":130,
    "UPC":1660051312
  },
  {
    "date_start":636854400000,
    "date_end":637372800000,
    "smoothed_cost_price":1.193011226,
    "STORE":124,
    "UPC":1660051312
  },
  {
    "date_start":637459200000,
    "date_end":637977600000,
    "smoothed_cost_price":1.1002873078,
    "STORE":74,
    "UPC":1660051312
  },
  {
    "date_start":638064000000,
    "date_end":638582400000,
    "smoothed_cost_price":1.1334885642,
    "STORE":12,
    "UPC":1660051312
  },
  {
    "date_start":638668800000,
    "date_end":639187200000,
    "smoothed_cost_price":1.1615446226,
    "STORE":93,
    "UPC":1660051312
  },
  {
    "date_start":639273600000,
    "date_end":639792000000,
    "smoothed_cost_price":1.1353839432,
    "STORE":113,
    "UPC":1660051312
  },
  {
    "date_start":639878400000,
    "date_end":640396800000,
    "smoothed_cost_price":1.1650809062,
    "STORE":124,
    "UPC":1660051312
  },
  {
    "date_start":640483200000,
    "date_end":641001600000,
    "smoothed_cost_price":1.1870783102,
    "STORE":130,
    "UPC":1660051312
  },
  {
    "date_start":641088000000,
    "date_end":641606400000,
    "smoothed_cost_price":1.0888331165,
    "STORE":100,
    "UPC":1660051312
  },
  {
    "date_start":641692800000,
    "date_end":642211200000,
    "smoothed_cost_price":1.0450972558,
    "STORE":111,
    "UPC":1660051312
  },
  {
    "date_start":642297600000,
    "date_end":642816000000,
    "smoothed_cost_price":1.0050436828,
    "STORE":130,
    "UPC":1660051312
  },
  {
    "date_start":642902400000,
    "date_end":643420800000,
    "smoothed_cost_price":0.9667150839,
    "STORE":93,
    "UPC":1660051312
  },
  {
    "date_start":643507200000,
    "date_end":644025600000,
    "smoothed_cost_price":0.9353127987,
    "STORE":121,
    "UPC":1660051312
  },
  {
    "date_start":644112000000,
    "date_end":644630400000,
    "smoothed_cost_price":0.9095772854,
    "STORE":128,
    "UPC":1660051312
  },
  {
    "date_start":644716800000,
    "date_end":645235200000,
    "smoothed_cost_price":0.8884700778,
    "STORE":32,
    "UPC":1660051312
  },
  {
    "date_start":645321600000,
    "date_end":645840000000,
    "smoothed_cost_price":0.8711651923,
    "STORE":121,
    "UPC":1660051312
  },
  {
    "date_start":645926400000,
    "date_end":646444800000,
    "smoothed_cost_price":0.8569641915,
    "STORE":137,
    "UPC":1660051312
  },
  {
    "date_start":646531200000,
    "date_end":647049600000,
    "smoothed_cost_price":0.8453025927,
    "STORE":105,
    "UPC":1660051312
  },
  {
    "date_start":647136000000,
    "date_end":647654400000,
    "smoothed_cost_price":0.8357156107,
    "STORE":128,
    "UPC":1660051312
  },
  {
    "date_start":647740800000,
    "date_end":648259200000,
    "smoothed_cost_price":0.8278315953,
    "STORE":100,
    "UPC":1660051312
  },
  {
    "date_start":648345600000,
    "date_end":648864000000,
    "smoothed_cost_price":0.8213365603,
    "STORE":102,
    "UPC":1660051312
  },
  {
    "date_start":648950400000,
    "date_end":649468800000,
    "smoothed_cost_price":0.8159823198,
    "STORE":114,
    "UPC":1660051312
  },
  {
    "date_start":649555200000,
    "date_end":650073600000,
    "smoothed_cost_price":0.8115593809,
    "STORE":122,
    "UPC":1660051312
  },
  {
    "date_start":650160000000,
    "date_end":650678400000,
    "smoothed_cost_price":0.8078979653,
    "STORE":137,
    "UPC":1660051312
  },
  {
    "date_start":650764800000,
    "date_end":651283200000,
    "smoothed_cost_price":0.8048593111,
    "STORE":137,
    "UPC":1660051312
  },
  {
    "date_start":651369600000,
    "date_end":651888000000,
    "smoothed_cost_price":0.8023299428,
    "STORE":137,
    "UPC":1660051312
  },
  {
    "date_start":651974400000,
    "date_end":652492800000,
    "smoothed_cost_price":0.8002164751,
    "STORE":93,
    "UPC":1660051312
  },
  {
    "date_start":652579200000,
    "date_end":653097600000,
    "smoothed_cost_price":0.7984435851,
    "STORE":109,
    "UPC":1660051312
  },
  {
    "date_start":653184000000,
    "date_end":653702400000,
    "smoothed_cost_price":0.7969546224,
    "STORE":113,
    "UPC":1660051312
  },
  {
    "date_start":653788800000,
    "date_end":654307200000,
    "smoothed_cost_price":0.795693782,
    "STORE":44,
    "UPC":1660051312
  },
  {
    "date_start":654393600000,
    "date_end":654912000000,
    "smoothed_cost_price":0.7946621852,
    "STORE":137,
    "UPC":1660051312
  },
  {
    "date_start":654998400000,
    "date_end":655516800000,
    "smoothed_cost_price":0.793818,
    "STORE":137,
    "UPC":1660051312
  },
  {
    "date_start":655603200000,
    "date_end":656121600000,
    "smoothed_cost_price":0.7931274546,
    "STORE":76,
    "UPC":1660051312
  },
  {
    "date_start":656208000000,
    "date_end":656726400000,
    "smoothed_cost_price":0.7925624628,
    "STORE":132,
    "UPC":1660051312
  },
  {
    "date_start":656812800000,
    "date_end":657331200000,
    "smoothed_cost_price":0.7920976514,
    "STORE":111,
    "UPC":1660051312
  },
  {
    "date_start":657417600000,
    "date_end":657936000000,
    "smoothed_cost_price":0.7917176693,
    "STORE":76,
    "UPC":1660051312
  },
  {
    "date_start":658022400000,
    "date_end":658540800000,
    "smoothed_cost_price":0.7914071916,
    "STORE":132,
    "UPC":1660051312
  },
  {
    "date_start":658627200000,
    "date_end":659145600000,
    "smoothed_cost_price":0.7911587931,
    "STORE":124,
    "UPC":1660051312
  },
  {
    "date_start":659232000000,
    "date_end":659750400000,
    "smoothed_cost_price":0.7909499292,
    "STORE":12,
    "UPC":1660051312
  },
  {
    "date_start":659836800000,
    "date_end":660355200000,
    "smoothed_cost_price":0.7907790406,
    "STORE":12,
    "UPC":1660051312
  },
  {
    "date_start":660441600000,
    "date_end":660960000000,
    "smoothed_cost_price":0.7906392226,
    "STORE":105,
    "UPC":1660051312
  },
  {
    "date_start":661046400000,
    "date_end":661564800000,
    "smoothed_cost_price":0.7905248261,
    "STORE":121,
    "UPC":1660051312
  },
  {
    "date_start":661651200000,
    "date_end":662169600000,
    "smoothed_cost_price":0.7904330395,
    "STORE":109,
    "UPC":1660051312
  },
  {
    "date_start":662256000000,
    "date_end":662774400000,
    "smoothed_cost_price":0.7585396649,
    "STORE":109,
    "UPC":1660051312
  },
  {
    "date_start":662860800000,
    "date_end":663379200000,
    "smoothed_cost_price":0.7648673369,
    "STORE":124,
    "UPC":1660051312
  },
  {
    "date_start":663465600000,
    "date_end":663984000000,
    "smoothed_cost_price":0.8348979979,
    "STORE":105,
    "UPC":1660051312
  },
  {
    "date_start":664070400000,
    "date_end":664588800000,
    "smoothed_cost_price":0.9409831271,
    "STORE":80,
    "UPC":1660051312
  },
  {
    "date_start":664675200000,
    "date_end":665193600000,
    "smoothed_cost_price":1.0277800509,
    "STORE":130,
    "UPC":1660051312
  },
  {
    "date_start":665280000000,
    "date_end":665798400000,
    "smoothed_cost_price":1.0500082235,
    "STORE":132,
    "UPC":1660051312
  },
  {
    "date_start":665884800000,
    "date_end":666403200000,
    "smoothed_cost_price":1.1169824026,
    "STORE":80,
    "UPC":1660051312
  },
  {
    "date_start":666489600000,
    "date_end":667008000000,
    "smoothed_cost_price":1.0866177839,
    "STORE":74,
    "UPC":1660051312
  },
  {
    "date_start":667094400000,
    "date_end":667612800000,
    "smoothed_cost_price":1.1469356793,
    "STORE":111,
    "UPC":1660051312
  },
  {
    "date_start":667699200000,
    "date_end":668217600000,
    "smoothed_cost_price":1.0384099194,
    "STORE":105,
    "UPC":1660051312
  },
  {
    "date_start":668304000000,
    "date_end":668822400000,
    "smoothed_cost_price":0.9496161159,
    "STORE":80,
    "UPC":1660051312
  },
  {
    "date_start":668908800000,
    "date_end":669427200000,
    "smoothed_cost_price":0.8769666403,
    "STORE":18,
    "UPC":1660051312
  },
  {
    "date_start":669513600000,
    "date_end":670032000000,
    "smoothed_cost_price":0.8175261602,
    "STORE":122,
    "UPC":1660051312
  },
  {
    "date_start":670118400000,
    "date_end":670636800000,
    "smoothed_cost_price":0.7688930402,
    "STORE":105,
    "UPC":1660051312
  },
  {
    "date_start":670723200000,
    "date_end":671241600000,
    "smoothed_cost_price":0.8825856276,
    "STORE":132,
    "UPC":1660051312
  },
  {
    "date_start":671328000000,
    "date_end":671846400000,
    "smoothed_cost_price":0.9312127862,
    "STORE":18,
    "UPC":1660051312
  },
  {
    "date_start":671932800000,
    "date_end":672451200000,
    "smoothed_cost_price":1.0197861357,
    "STORE":102,
    "UPC":1660051312
  },
  {
    "date_start":672537600000,
    "date_end":673056000000,
    "smoothed_cost_price":1.0931629898,
    "STORE":93,
    "UPC":1660051312
  },
  {
    "date_start":673142400000,
    "date_end":673660800000,
    "smoothed_cost_price":1.1035033553,
    "STORE":44,
    "UPC":1660051312
  },
  {
    "date_start":673747200000,
    "date_end":674265600000,
    "smoothed_cost_price":1.1616588967,
    "STORE":80,
    "UPC":1660051312
  },
  {
    "date_start":674352000000,
    "date_end":674870400000,
    "smoothed_cost_price":1.2092407034,
    "STORE":113,
    "UPC":1660051312
  },
  {
    "date_start":674956800000,
    "date_end":675475200000,
    "smoothed_cost_price":1.2360396967,
    "STORE":32,
    "UPC":1660051312
  },
  {
    "date_start":675561600000,
    "date_end":676080000000,
    "smoothed_cost_price":1.2664608125,
    "STORE":100,
    "UPC":1660051312
  },
  {
    "date_start":676166400000,
    "date_end":676684800000,
    "smoothed_cost_price":1.1362032102,
    "STORE":18,
    "UPC":1660051312
  },
  {
    "date_start":676771200000,
    "date_end":677289600000,
    "smoothed_cost_price":1.0878095356,
    "STORE":137,
    "UPC":1660051312
  },
  {
    "date_start":677376000000,
    "date_end":677894400000,
    "smoothed_cost_price":1.048214711,
    "STORE":107,
    "UPC":1660051312
  },
  {
    "date_start":677980800000,
    "date_end":678499200000,
    "smoothed_cost_price":1.0158189453,
    "STORE":80,
    "UPC":1660051312
  },
  {
    "date_start":678585600000,
    "date_end":679104000000,
    "smoothed_cost_price":0.9893133189,
    "STORE":12,
    "UPC":1660051312
  },
  {
    "date_start":679190400000,
    "date_end":679708800000,
    "smoothed_cost_price":0.9676268973,
    "STORE":44,
    "UPC":1660051312
  },
  {
    "date_start":679795200000,
    "date_end":680313600000,
    "smoothed_cost_price":0.9498834614,
    "STORE":105,
    "UPC":1660051312
  },
  {
    "date_start":680400000000,
    "date_end":680918400000,
    "smoothed_cost_price":0.9353661048,
    "STORE":12,
    "UPC":1660051312
  },
  {
    "date_start":681004800000,
    "date_end":681523200000,
    "smoothed_cost_price":0.9234882676,
    "STORE":98,
    "UPC":1660051312
  },
  {
    "date_start":681609600000,
    "date_end":682128000000,
    "smoothed_cost_price":0.9137700371,
    "STORE":121,
    "UPC":1660051312
  },
  {
    "date_start":682214400000,
    "date_end":682732800000,
    "smoothed_cost_price":0.9058140304,
    "STORE":130,
    "UPC":1660051312
  },
  {
    "date_start":682819200000,
    "date_end":683337600000,
    "smoothed_cost_price":0.8993092976,
    "STORE":113,
    "UPC":1660051312
  },
  {
    "date_start":683424000000,
    "date_end":683942400000,
    "smoothed_cost_price":0.8902527548,
    "STORE":137,
    "UPC":1660051312
  },
  {
    "date_start":684028800000,
    "date_end":684547200000,
    "smoothed_cost_price":0.8652121062,
    "STORE":105,
    "UPC":1660051312
  },
  {
    "date_start":684633600000,
    "date_end":685152000000,
    "smoothed_cost_price":0.8442697233,
    "STORE":18,
    "UPC":1660051312
  },
  {
    "date_start":685238400000,
    "date_end":685756800000,
    "smoothed_cost_price":0.8271350463,
    "STORE":98,
    "UPC":1660051312
  },
  {
    "date_start":685843200000,
    "date_end":686361600000,
    "smoothed_cost_price":0.7767548561,
    "STORE":32,
    "UPC":1660051312
  },
  {
    "date_start":686448000000,
    "date_end":686966400000,
    "smoothed_cost_price":0.7792448519,
    "STORE":44,
    "UPC":1660051312
  },
  {
    "date_start":687052800000,
    "date_end":687571200000,
    "smoothed_cost_price":0.795752697,
    "STORE":102,
    "UPC":1660051312
  },
  {
    "date_start":687657600000,
    "date_end":688176000000,
    "smoothed_cost_price":0.8092591158,
    "STORE":124,
    "UPC":1660051312
  },
  {
    "date_start":688262400000,
    "date_end":688780800000,
    "smoothed_cost_price":0.8170222917,
    "STORE":12,
    "UPC":1660051312
  },
  {
    "date_start":688867200000,
    "date_end":689385600000,
    "smoothed_cost_price":0.8121127841,
    "STORE":124,
    "UPC":1660051312
  },
  {
    "date_start":689472000000,
    "date_end":689990400000,
    "smoothed_cost_price":0.8080959143,
    "STORE":137,
    "UPC":1660051312
  },
  {
    "date_start":690076800000,
    "date_end":690595200000,
    "smoothed_cost_price":0.8048093844,
    "STORE":128,
    "UPC":1660051312
  },
  {
    "date_start":690681600000,
    "date_end":691200000000,
    "smoothed_cost_price":0.8021204054,
    "STORE":130,
    "UPC":1660051312
  },
  {
    "date_start":691286400000,
    "date_end":691804800000,
    "smoothed_cost_price":0.7999203317,
    "STORE":128,
    "UPC":1660051312
  },
  {
    "date_start":691891200000,
    "date_end":692409600000,
    "smoothed_cost_price":0.7981235517,
    "STORE":12,
    "UPC":1660051312
  },
  {
    "date_start":692496000000,
    "date_end":693014400000,
    "smoothed_cost_price":0.7966524059,
    "STORE":80,
    "UPC":1660051312
  },
  {
    "date_start":693100800000,
    "date_end":693619200000,
    "smoothed_cost_price":0.7954465139,
    "STORE":18,
    "UPC":1660051312
  },
  {
    "date_start":693705600000,
    "date_end":694224000000,
    "smoothed_cost_price":0.7944591326,
    "STORE":32,
    "UPC":1660051312
  },
  {
    "date_start":694310400000,
    "date_end":694828800000,
    "smoothed_cost_price":0.7936520176,
    "STORE":93,
    "UPC":1660051312
  },
  {
    "date_start":694915200000,
    "date_end":695433600000,
    "smoothed_cost_price":0.8077141508,
    "STORE":80,
    "UPC":1660051312
  },
  {
    "date_start":695520000000,
    "date_end":696038400000,
    "smoothed_cost_price":0.7608650324,
    "STORE":113,
    "UPC":1660051312
  },
  {
    "date_start":696124800000,
    "date_end":696643200000,
    "smoothed_cost_price":0.7057162387,
    "STORE":12,
    "UPC":1660051312
  },
  {
    "date_start":696729600000,
    "date_end":697248000000,
    "smoothed_cost_price":0.6410472862,
    "STORE":93,
    "UPC":1660051312
  },
  {
    "date_start":697334400000,
    "date_end":697852800000,
    "smoothed_cost_price":0.6243500069,
    "STORE":130,
    "UPC":1660051312
  },
  {
    "date_start":697939200000,
    "date_end":698457600000,
    "smoothed_cost_price":0.5744749147,
    "STORE":111,
    "UPC":1660051312
  },
  {
    "date_start":698544000000,
    "date_end":699062400000,
    "smoothed_cost_price":0.5700329302,
    "STORE":44,
    "UPC":1660051312
  },
  {
    "date_start":699148800000,
    "date_end":699667200000,
    "smoothed_cost_price":0.5663985793,
    "STORE":93,
    "UPC":1660051312
  },
  {
    "date_start":699753600000,
    "date_end":700272000000,
    "smoothed_cost_price":0.5634250194,
    "STORE":102,
    "UPC":1660051312
  },
  {
    "date_start":700358400000,
    "date_end":700876800000,
    "smoothed_cost_price":0.5609921068,
    "STORE":44,
    "UPC":1660051312
  },
  {
    "date_start":700963200000,
    "date_end":701481600000,
    "smoothed_cost_price":0.5226366328,
    "STORE":137,
    "UPC":1660051312
  },
  {
    "date_start":701568000000,
    "date_end":702086400000,
    "smoothed_cost_price":0.5267109609,
    "STORE":132,
    "UPC":1660051312
  },
  {
    "date_start":702172800000,
    "date_end":702691200000,
    "smoothed_cost_price":0.5309533317,
    "STORE":105,
    "UPC":1660051312
  },
  {
    "date_start":702777600000,
    "date_end":703296000000,
    "smoothed_cost_price":0.5344243623,
    "STORE":105,
    "UPC":1660051312
  },
  {
    "date_start":703382400000,
    "date_end":703900800000,
    "smoothed_cost_price":0.5372642964,
    "STORE":130,
    "UPC":1660051312
  },
  {
    "date_start":703987200000,
    "date_end":704505600000,
    "smoothed_cost_price":0.5580363789,
    "STORE":121,
    "UPC":1660051312
  },
  {
    "date_start":704592000000,
    "date_end":705110400000,
    "smoothed_cost_price":0.6002152191,
    "STORE":32,
    "UPC":1660051312
  },
  {
    "date_start":705196800000,
    "date_end":705715200000,
    "smoothed_cost_price":0.6347251793,
    "STORE":102,
    "UPC":1660051312
  },
  {
    "date_start":705801600000,
    "date_end":706320000000,
    "smoothed_cost_price":0.6629606012,
    "STORE":128,
    "UPC":1660051312
  },
  {
    "date_start":706406400000,
    "date_end":706924800000,
    "smoothed_cost_price":0.6860623101,
    "STORE":76,
    "UPC":1660051312
  },
  {
    "date_start":707011200000,
    "date_end":707529600000,
    "smoothed_cost_price":0.7049629658,
    "STORE":32,
    "UPC":1660051312
  },
  {
    "date_start":707616000000,
    "date_end":708134400000,
    "smoothed_cost_price":0.7204283054,
    "STORE":100,
    "UPC":1660051312
  },
  {
    "date_start":708220800000,
    "date_end":708739200000,
    "smoothed_cost_price":0.7330813408,
    "STORE":128,
    "UPC":1660051312
  },
  {
    "date_start":708825600000,
    "date_end":709344000000,
    "smoothed_cost_price":0.7434338243,
    "STORE":98,
    "UPC":1660051312
  },
  {
    "date_start":709430400000,
    "date_end":709948800000,
    "smoothed_cost_price":0.7519074092,
    "STORE":80,
    "UPC":1660051312
  },
  {
    "date_start":710035200000,
    "date_end":710553600000,
    "smoothed_cost_price":0.7459655848,
    "STORE":93,
    "UPC":1660051312
  },
  {
    "date_start":710640000000,
    "date_end":711158400000,
    "smoothed_cost_price":0.7103434785,
    "STORE":18,
    "UPC":1660051312
  },
  {
    "date_start":711244800000,
    "date_end":711763200000,
    "smoothed_cost_price":0.8411821188,
    "STORE":32,
    "UPC":1660051312
  },
  {
    "date_start":711849600000,
    "date_end":712368000000,
    "smoothed_cost_price":0.9482319154,
    "STORE":100,
    "UPC":1660051312
  },
  {
    "date_start":712454400000,
    "date_end":712972800000,
    "smoothed_cost_price":1.0358181126,
    "STORE":98,
    "UPC":1660051312
  },
  {
    "date_start":713059200000,
    "date_end":713577600000,
    "smoothed_cost_price":1.1074795466,
    "STORE":128,
    "UPC":1660051312
  },
  {
    "date_start":713664000000,
    "date_end":714182400000,
    "smoothed_cost_price":1.1661116291,
    "STORE":109,
    "UPC":1660051312
  },
  {
    "date_start":714268800000,
    "date_end":714787200000,
    "smoothed_cost_price":1.2140833329,
    "STORE":80,
    "UPC":1660051312
  },
  {
    "date_start":714873600000,
    "date_end":715392000000,
    "smoothed_cost_price":1.2533329087,
    "STORE":44,
    "UPC":1660051312
  },
  {
    "date_start":715478400000,
    "date_end":715996800000,
    "smoothed_cost_price":1.285446198,
    "STORE":76,
    "UPC":1660051312
  },
  {
    "date_start":716083200000,
    "date_end":716601600000,
    "smoothed_cost_price":1.3117207075,
    "STORE":12,
    "UPC":1660051312
  },
  {
    "date_start":716688000000,
    "date_end":717206400000,
    "smoothed_cost_price":1.3332180334,
    "STORE":105,
    "UPC":1660051312
  },
  {
    "date_start":717292800000,
    "date_end":717811200000,
    "smoothed_cost_price":1.3461777546,
    "STORE":105,
    "UPC":1660051312
  },
  {
    "date_start":717897600000,
    "date_end":718416000000,
    "smoothed_cost_price":1.2450581629,
    "STORE":32,
    "UPC":1660051312
  },
  {
    "date_start":718502400000,
    "date_end":719020800000,
    "smoothed_cost_price":1.1623239514,
    "STORE":109,
    "UPC":1660051312
  },
  {
    "date_start":719107200000,
    "date_end":719625600000,
    "smoothed_cost_price":1.0946323239,
    "STORE":132,
    "UPC":1660051312
  },
  {
    "date_start":719712000000,
    "date_end":720230400000,
    "smoothed_cost_price":1.039248265,
    "STORE":93,
    "UPC":1660051312
  },
  {
    "date_start":720316800000,
    "date_end":720835200000,
    "smoothed_cost_price":0.993934035,
    "STORE":32,
    "UPC":1660051312
  },
  {
    "date_start":720921600000,
    "date_end":721440000000,
    "smoothed_cost_price":0.9568596044,
    "STORE":107,
    "UPC":1660051312
  },
  {
    "date_start":721526400000,
    "date_end":722044800000,
    "smoothed_cost_price":0.9265255551,
    "STORE":122,
    "UPC":1660051312
  },
  {
    "date_start":722131200000,
    "date_end":722649600000,
    "smoothed_cost_price":0.9017056208,
    "STORE":76,
    "UPC":1660051312
  },
  {
    "date_start":722736000000,
    "date_end":723254400000,
    "smoothed_cost_price":0.8814033565,
    "STORE":121,
    "UPC":1660051312
  },
  {
    "date_start":723340800000,
    "date_end":723859200000,
    "smoothed_cost_price":0.8647882007,
    "STORE":100,
    "UPC":1660051312
  },
  {
    "date_start":723945600000,
    "date_end":724464000000,
    "smoothed_cost_price":0.8511939824,
    "STORE":128,
    "UPC":1660051312
  },
  {
    "date_start":724550400000,
    "date_end":725068800000,
    "smoothed_cost_price":0.8400714402,
    "STORE":76,
    "UPC":1660051312
  },
  {
    "date_start":725155200000,
    "date_end":725673600000,
    "smoothed_cost_price":0.8309711783,
    "STORE":93,
    "UPC":1660051312
  },
  {
    "date_start":725760000000,
    "date_end":726278400000,
    "smoothed_cost_price":0.8235255095,
    "STORE":44,
    "UPC":1660051312
  },
  {
    "date_start":726364800000,
    "date_end":726883200000,
    "smoothed_cost_price":0.8402425987,
    "STORE":114,
    "UPC":1660051312
  },
  {
    "date_start":726969600000,
    "date_end":727488000000,
    "smoothed_cost_price":0.9474632171,
    "STORE":105,
    "UPC":1660051312
  },
  {
    "date_start":727574400000,
    "date_end":728092800000,
    "smoothed_cost_price":1.0351891776,
    "STORE":111,
    "UPC":1660051312
  },
  {
    "date_start":728179200000,
    "date_end":728697600000,
    "smoothed_cost_price":1.1069649635,
    "STORE":74,
    "UPC":1660051312
  },
  {
    "date_start":728784000000,
    "date_end":729302400000,
    "smoothed_cost_price":1.1656906065,
    "STORE":12,
    "UPC":1660051312
  },
  {
    "date_start":729388800000,
    "date_end":729907200000,
    "smoothed_cost_price":1.2137388599,
    "STORE":18,
    "UPC":1660051312
  },
  {
    "date_start":729993600000,
    "date_end":730512000000,
    "smoothed_cost_price":1.2530510672,
    "STORE":111,
    "UPC":1660051312
  },
  {
    "date_start":730598400000,
    "date_end":731116800000,
    "smoothed_cost_price":1.2852156004,
    "STORE":107,
    "UPC":1660051312
  },
  {
    "date_start":731203200000,
    "date_end":731721600000,
    "smoothed_cost_price":1.3115320367,
    "STORE":44,
    "UPC":1660051312
  },
  {
    "date_start":731808000000,
    "date_end":732326400000,
    "smoothed_cost_price":1.3330634543,
    "STORE":12,
    "UPC":1660051312
  },
  {
    "date_start":732412800000,
    "date_end":732931200000,
    "smoothed_cost_price":1.3506802808,
    "STORE":44,
    "UPC":1660051312
  },
  {
    "date_start":733017600000,
    "date_end":733536000000,
    "smoothed_cost_price":1.3650940479,
    "STORE":114,
    "UPC":1660051312
  },
  {
    "date_start":733622400000,
    "date_end":734140800000,
    "smoothed_cost_price":1.3768871301,
    "STORE":128,
    "UPC":1660051312
  },
  {
    "date_start":734227200000,
    "date_end":734745600000,
    "smoothed_cost_price":1.3865360155,
    "STORE":44,
    "UPC":1660051312
  },
  {
    "date_start":734832000000,
    "date_end":735350400000,
    "smoothed_cost_price":1.3944307854,
    "STORE":18,
    "UPC":1660051312
  },
  {
    "date_start":735436800000,
    "date_end":735955200000,
    "smoothed_cost_price":1.4008903093,
    "STORE":74,
    "UPC":1660051312
  },
  {
    "date_start":736041600000,
    "date_end":736560000000,
    "smoothed_cost_price":1.4061754273,
    "STORE":32,
    "UPC":1660051312
  },
  {
    "date_start":736646400000,
    "date_end":737164800000,
    "smoothed_cost_price":1.410499342,
    "STORE":98,
    "UPC":1660051312
  },
  {
    "date_start":737251200000,
    "date_end":737769600000,
    "smoothed_cost_price":1.4140363708,
    "STORE":132,
    "UPC":1660051312
  },
  {
    "date_start":737856000000,
    "date_end":738374400000,
    "smoothed_cost_price":1.4169308488,
    "STORE":100,
    "UPC":1660051312
  },
  {
    "date_start":738460800000,
    "date_end":738979200000,
    "smoothed_cost_price":1.4192990581,
    "STORE":113,
    "UPC":1660051312
  },
  {
    "date_start":739065600000,
    "date_end":739584000000,
    "smoothed_cost_price":1.4212366839,
    "STORE":12,
    "UPC":1660051312
  },
  {
    "date_start":739670400000,
    "date_end":740188800000,
    "smoothed_cost_price":1.4228220141,
    "STORE":80,
    "UPC":1660051312
  },
  {
    "date_start":740275200000,
    "date_end":740793600000,
    "smoothed_cost_price":1.4241191025,
    "STORE":114,
    "UPC":1660051312
  },
  {
    "date_start":740880000000,
    "date_end":741398400000,
    "smoothed_cost_price":1.4251803566,
    "STORE":124,
    "UPC":1660051312
  },
  {
    "date_start":741484800000,
    "date_end":742003200000,
    "smoothed_cost_price":1.4260499281,
    "STORE":32,
    "UPC":1660051312
  },
  {
    "date_start":742089600000,
    "date_end":742608000000,
    "smoothed_cost_price":1.4267595737,
    "STORE":93,
    "UPC":1660051312
  },
  {
    "date_start":742694400000,
    "date_end":743212800000,
    "smoothed_cost_price":1.4273407421,
    "STORE":105,
    "UPC":1660051312
  },
  {
    "date_start":743299200000,
    "date_end":743817600000,
    "smoothed_cost_price":1.4278162436,
    "STORE":130,
    "UPC":1660051312
  },
  {
    "date_start":743904000000,
    "date_end":744422400000,
    "smoothed_cost_price":1.4282052902,
    "STORE":114,
    "UPC":1660051312
  },
  {
    "date_start":744508800000,
    "date_end":745027200000,
    "smoothed_cost_price":1.4285236011,
    "STORE":93,
    "UPC":1660051312
  },
  {
    "date_start":745113600000,
    "date_end":745632000000,
    "smoothed_cost_price":1.4287840372,
    "STORE":122,
    "UPC":1660051312
  },
  {
    "date_start":745718400000,
    "date_end":746236800000,
    "smoothed_cost_price":1.4289971214,
    "STORE":32,
    "UPC":1660051312
  },
  {
    "date_start":746323200000,
    "date_end":746841600000,
    "smoothed_cost_price":1.4291714629,
    "STORE":137,
    "UPC":1660051312
  },
  {
    "date_start":746928000000,
    "date_end":747446400000,
    "smoothed_cost_price":1.429314106,
    "STORE":105,
    "UPC":1660051312
  },
  {
    "date_start":747532800000,
    "date_end":748051200000,
    "smoothed_cost_price":1.429430814,
    "STORE":121,
    "UPC":1660051312
  },
  {
    "date_start":748137600000,
    "date_end":748656000000,
    "smoothed_cost_price":1.4295263024,
    "STORE":122,
    "UPC":1660051312
  },
  {
    "date_start":748742400000,
    "date_end":749260800000,
    "smoothed_cost_price":1.4296044292,
    "STORE":93,
    "UPC":1660051312
  },
  {
    "date_start":749347200000,
    "date_end":749865600000,
    "smoothed_cost_price":1.4296683512,
    "STORE":100,
    "UPC":1660051312
  },
  {
    "date_start":749952000000,
    "date_end":750470400000,
    "smoothed_cost_price":1.429720651,
    "STORE":102,
    "UPC":1660051312
  },
  {
    "date_start":750556800000,
    "date_end":751075200000,
    "smoothed_cost_price":1.4297634417,
    "STORE":130,
    "UPC":1660051312
  },
  {
    "date_start":751161600000,
    "date_end":751680000000,
    "smoothed_cost_price":1.4297984523,
    "STORE":98,
    "UPC":1660051312
  },
  {
    "date_start":751766400000,
    "date_end":752284800000,
    "smoothed_cost_price":1.4298270973,
    "STORE":109,
    "UPC":1660051312
  },
  {
    "date_start":752371200000,
    "date_end":752889600000,
    "smoothed_cost_price":1.4298505342,
    "STORE":102,
    "UPC":1660051312
  },
  {
    "date_start":752976000000,
    "date_end":753494400000,
    "smoothed_cost_price":1.4298697098,
    "STORE":76,
    "UPC":1660051312
  },
  {
    "date_start":753580800000,
    "date_end":754099200000,
    "smoothed_cost_price":1.4298853989,
    "STORE":109,
    "UPC":1660051312
  },
  {
    "date_start":754185600000,
    "date_end":754704000000,
    "smoothed_cost_price":1.4298982355,
    "STORE":93,
    "UPC":1660051312
  },
  {
    "date_start":754790400000,
    "date_end":755308800000,
    "smoothed_cost_price":1.4299087381,
    "STORE":130,
    "UPC":1660051312
  },
  {
    "date_start":755395200000,
    "date_end":755913600000,
    "smoothed_cost_price":1.4299173312,
    "STORE":80,
    "UPC":1660051312
  },
  {
    "date_start":756000000000,
    "date_end":756518400000,
    "smoothed_cost_price":1.4299243619,
    "STORE":18,
    "UPC":1660051312
  },
  {
    "date_start":756604800000,
    "date_end":757123200000,
    "smoothed_cost_price":1.4299301143,
    "STORE":93,
    "UPC":1660051312
  },
  {
    "date_start":757209600000,
    "date_end":757728000000,
    "smoothed_cost_price":1.4193305556,
    "STORE":122,
    "UPC":1660051312
  },
  {
    "date_start":757814400000,
    "date_end":758332800000,
    "smoothed_cost_price":1.4212624546,
    "STORE":137,
    "UPC":1660051312
  },
  {
    "date_start":758419200000,
    "date_end":758937600000,
    "smoothed_cost_price":1.4228430992,
    "STORE":121,
    "UPC":1660051312
  },
  {
    "date_start":759024000000,
    "date_end":759542400000,
    "smoothed_cost_price":1.4241363539,
    "STORE":128,
    "UPC":1660051312
  },
  {
    "date_start":759628800000,
    "date_end":760147200000,
    "smoothed_cost_price":1.4251957441,
    "STORE":124,
    "UPC":1660051312
  },
  {
    "date_start":760233600000,
    "date_end":760752000000,
    "smoothed_cost_price":1.4260593967,
    "STORE":114,
    "UPC":1660051312
  },
  {
    "date_start":760838400000,
    "date_end":761356800000,
    "smoothed_cost_price":1.42676787,
    "STORE":44,
    "UPC":1660051312
  },
  {
    "date_start":761443200000,
    "date_end":761961600000,
    "smoothed_cost_price":1.4273456815,
    "STORE":76,
    "UPC":1660051312
  },
  {
    "date_start":762048000000,
    "date_end":762566400000,
    "smoothed_cost_price":1.4278202849,
    "STORE":98,
    "UPC":1660051312
  },
  {
    "date_start":762652800000,
    "date_end":763171200000,
    "smoothed_cost_price":1.3027665967,
    "STORE":109,
    "UPC":1660051312
  },
  {
    "date_start":763257600000,
    "date_end":763776000000,
    "smoothed_cost_price":1.3075514428,
    "STORE":80,
    "UPC":1660051312
  },
  {
    "date_start":763862400000,
    "date_end":764380800000,
    "smoothed_cost_price":1.3259529418,
    "STORE":98,
    "UPC":1660051312
  },
  {
    "date_start":764467200000,
    "date_end":764985600000,
    "smoothed_cost_price":1.3393899888,
    "STORE":113,
    "UPC":1660051312
  },
  {
    "date_start":765072000000,
    "date_end":765590400000,
    "smoothed_cost_price":1.3291144613,
    "STORE":107,
    "UPC":1660051312
  },
  {
    "date_start":765676800000,
    "date_end":766195200000,
    "smoothed_cost_price":1.2635797662,
    "STORE":137,
    "UPC":1660051312
  },
  {
    "date_start":766281600000,
    "date_end":766800000000,
    "smoothed_cost_price":1.1976988251,
    "STORE":128,
    "UPC":1660051312
  },
  {
    "date_start":766886400000,
    "date_end":767404800000,
    "smoothed_cost_price":1.1388065916,
    "STORE":109,
    "UPC":1660051312
  },
  {
    "date_start":767491200000,
    "date_end":768009600000,
    "smoothed_cost_price":1.0889105632,
    "STORE":130,
    "UPC":1660051312
  },
  {
    "date_start":768096000000,
    "date_end":768614400000,
    "smoothed_cost_price":1.0474355661,
    "STORE":111,
    "UPC":1660051312
  },
  {
    "date_start":768700800000,
    "date_end":769219200000,
    "smoothed_cost_price":1.0132567537,
    "STORE":132,
    "UPC":1660051312
  },
  {
    "date_start":769305600000,
    "date_end":769824000000,
    "smoothed_cost_price":0.9855277721,
    "STORE":98,
    "UPC":1660051312
  },
  {
    "date_start":769910400000,
    "date_end":770428800000,
    "smoothed_cost_price":0.9637272997,
    "STORE":100,
    "UPC":1660051312
  },
  {
    "date_start":770515200000,
    "date_end":771033600000,
    "smoothed_cost_price":0.9467774257,
    "STORE":114,
    "UPC":1660051312
  },
  {
    "date_start":771120000000,
    "date_end":771638400000,
    "smoothed_cost_price":0.9342363899,
    "STORE":44,
    "UPC":1660051312
  },
  {
    "date_start":771724800000,
    "date_end":772243200000,
    "smoothed_cost_price":0.9268031567,
    "STORE":32,
    "UPC":1660051312
  },
  {
    "date_start":772329600000,
    "date_end":772848000000,
    "smoothed_cost_price":0.9247610347,
    "STORE":130,
    "UPC":1660051312
  },
  {
    "date_start":772934400000,
    "date_end":773452800000,
    "smoothed_cost_price":0.9289060469,
    "STORE":105,
    "UPC":1660051312
  },
  {
    "date_start":773539200000,
    "date_end":774057600000,
    "smoothed_cost_price":0.9500119264,
    "STORE":121,
    "UPC":1660051312
  },
  {
    "date_start":774144000000,
    "date_end":774662400000,
    "smoothed_cost_price":1.0159203306,
    "STORE":105,
    "UPC":1660051312
  },
  {
    "date_start":779587200000,
    "date_end":780105600000,
    "smoothed_cost_price":1.080771087,
    "STORE":114,
    "UPC":1660051312
  },
  {
    "date_start":780192000000,
    "date_end":780710400000,
    "smoothed_cost_price":1.1410195535,
    "STORE":128,
    "UPC":1660051312
  },
  {
    "date_start":780796800000,
    "date_end":781315200000,
    "smoothed_cost_price":1.1497249907,
    "STORE":32,
    "UPC":1660051312
  },
  {
    "date_start":781401600000,
    "date_end":781920000000,
    "smoothed_cost_price":1.0842658561,
    "STORE":76,
    "UPC":1660051312
  },
  {
    "date_start":782006400000,
    "date_end":782524800000,
    "smoothed_cost_price":1.102251756,
    "STORE":130,
    "UPC":1660051312
  },
  {
    "date_start":782611200000,
    "date_end":783129600000,
    "smoothed_cost_price":1.1569786463,
    "STORE":76,
    "UPC":1660051312
  },
  {
    "date_start":783216000000,
    "date_end":783734400000,
    "smoothed_cost_price":1.1627824303,
    "STORE":137,
    "UPC":1660051312
  },
  {
    "date_start":783820800000,
    "date_end":784339200000,
    "smoothed_cost_price":1.0949492157,
    "STORE":76,
    "UPC":1660051312
  },
  {
    "date_start":784425600000,
    "date_end":784944000000,
    "smoothed_cost_price":1.0394447825,
    "STORE":32,
    "UPC":1660051312
  },
  {
    "date_start":785030400000,
    "date_end":785548800000,
    "smoothed_cost_price":1.025229216,
    "STORE":102,
    "UPC":1660051312
  },
  {
    "date_start":785635200000,
    "date_end":786153600000,
    "smoothed_cost_price":1.0514606919,
    "STORE":100,
    "UPC":1660051312
  },
  {
    "date_start":786240000000,
    "date_end":786758400000,
    "smoothed_cost_price":1.0729267328,
    "STORE":80,
    "UPC":1660051312
  },
  {
    "date_start":786844800000,
    "date_end":787363200000,
    "smoothed_cost_price":1.0905016298,
    "STORE":76,
    "UPC":1660051312
  },
  {
    "date_start":787449600000,
    "date_end":787968000000,
    "smoothed_cost_price":1.1048676365,
    "STORE":132,
    "UPC":1660051312
  },
  {
    "date_start":788054400000,
    "date_end":788572800000,
    "smoothed_cost_price":1.1166629753,
    "STORE":76,
    "UPC":1660051312
  },
  {
    "date_start":788659200000,
    "date_end":789177600000,
    "smoothed_cost_price":1.1250484192,
    "STORE":124,
    "UPC":1660051312
  },
  {
    "date_start":789264000000,
    "date_end":789782400000,
    "smoothed_cost_price":1.1578497597,
    "STORE":128,
    "UPC":1660051312
  },
  {
    "date_start":789868800000,
    "date_end":790387200000,
    "smoothed_cost_price":1.207350167,
    "STORE":114,
    "UPC":1660051312
  },
  {
    "date_start":790473600000,
    "date_end":790992000000,
    "smoothed_cost_price":1.2005123185,
    "STORE":74,
    "UPC":1660051312
  },
  {
    "date_start":791078400000,
    "date_end":791596800000,
    "smoothed_cost_price":1.1936524272,
    "STORE":128,
    "UPC":1660051312
  },
  {
    "date_start":791683200000,
    "date_end":792201600000,
    "smoothed_cost_price":1.2139803117,
    "STORE":121,
    "UPC":1660051312
  },
  {
    "date_start":792288000000,
    "date_end":792806400000,
    "smoothed_cost_price":1.2532751641,
    "STORE":18,
    "UPC":1660051312
  },
  {
    "date_start":792892800000,
    "date_end":793411200000,
    "smoothed_cost_price":1.24641096,
    "STORE":32,
    "UPC":1660051312
  },
  {
    "date_start":793497600000,
    "date_end":794016000000,
    "smoothed_cost_price":1.1969972552,
    "STORE":137,
    "UPC":1660051312
  },
  {
    "date_start":794102400000,
    "date_end":794620800000,
    "smoothed_cost_price":1.1770110876,
    "STORE":111,
    "UPC":1660051312
  },
  {
    "date_start":794707200000,
    "date_end":795225600000,
    "smoothed_cost_price":1.1756538519,
    "STORE":105,
    "UPC":1660051312
  },
  {
    "date_start":795312000000,
    "date_end":795830400000,
    "smoothed_cost_price":1.1746435152,
    "STORE":12,
    "UPC":1660051312
  },
  {
    "date_start":795916800000,
    "date_end":796435200000,
    "smoothed_cost_price":1.1688490806,
    "STORE":76,
    "UPC":1660051312
  },
  {
    "date_start":796521600000,
    "date_end":797040000000,
    "smoothed_cost_price":1.1240607175,
    "STORE":113,
    "UPC":1660051312
  },
  {
    "date_start":797126400000,
    "date_end":797644800000,
    "smoothed_cost_price":1.1323628598,
    "STORE":98,
    "UPC":1660051312
  },
  {
    "date_start":797731200000,
    "date_end":798249600000,
    "smoothed_cost_price":1.1391720747,
    "STORE":121,
    "UPC":1660051312
  },
  {
    "date_start":798336000000,
    "date_end":798854400000,
    "smoothed_cost_price":1.1408925005,
    "STORE":132,
    "UPC":1660051312
  },
  {
    "date_start":798940800000,
    "date_end":799459200000,
    "smoothed_cost_price":1.110638258,
    "STORE":12,
    "UPC":1660051312
  },
  {
    "date_start":799545600000,
    "date_end":800064000000,
    "smoothed_cost_price":1.085626658,
    "STORE":113,
    "UPC":1660051312
  },
  {
    "date_start":800150400000,
    "date_end":800668800000,
    "smoothed_cost_price":1.0599296596,
    "STORE":102,
    "UPC":1660051312
  },
  {
    "date_start":800755200000,
    "date_end":801273600000,
    "smoothed_cost_price":1.0389193048,
    "STORE":132,
    "UPC":1660051312
  },
  {
    "date_start":801360000000,
    "date_end":801878400000,
    "smoothed_cost_price":1.0594118706,
    "STORE":102,
    "UPC":1660051312
  },
  {
    "date_start":801964800000,
    "date_end":802483200000,
    "smoothed_cost_price":1.0787825684,
    "STORE":122,
    "UPC":1660051312
  },
  {
    "date_start":802569600000,
    "date_end":803088000000,
    "smoothed_cost_price":1.0950664499,
    "STORE":137,
    "UPC":1660051312
  },
  {
    "date_start":803174400000,
    "date_end":803692800000,
    "smoothed_cost_price":1.1086328757,
    "STORE":121,
    "UPC":1660051312
  },
  {
    "date_start":803779200000,
    "date_end":804297600000,
    "smoothed_cost_price":1.1192019362,
    "STORE":100,
    "UPC":1660051312
  },
  {
    "date_start":804384000000,
    "date_end":804902400000,
    "smoothed_cost_price":1.1280366069,
    "STORE":122,
    "UPC":1660051312
  },
  {
    "date_start":804988800000,
    "date_end":805507200000,
    "smoothed_cost_price":1.1356194435,
    "STORE":18,
    "UPC":1660051312
  },
  {
    "date_start":805593600000,
    "date_end":806112000000,
    "smoothed_cost_price":1.1416738477,
    "STORE":137,
    "UPC":1660051312
  },
  {
    "date_start":806198400000,
    "date_end":806716800000,
    "smoothed_cost_price":1.1113753375,
    "STORE":74,
    "UPC":1660051312
  },
  {
    "date_start":806803200000,
    "date_end":807321600000,
    "smoothed_cost_price":1.1194659504,
    "STORE":32,
    "UPC":1660051312
  },
  {
    "date_start":807408000000,
    "date_end":807926400000,
    "smoothed_cost_price":1.1286715958,
    "STORE":18,
    "UPC":1660051312
  },
  {
    "date_start":808012800000,
    "date_end":808531200000,
    "smoothed_cost_price":1.1362034874,
    "STORE":113,
    "UPC":1660051312
  },
  {
    "date_start":808617600000,
    "date_end":809136000000,
    "smoothed_cost_price":1.1423438685,
    "STORE":18,
    "UPC":1660051312
  },
  {
    "date_start":809222400000,
    "date_end":809740800000,
    "smoothed_cost_price":1.1429864909,
    "STORE":44,
    "UPC":1660051312
  },
  {
    "date_start":809827200000,
    "date_end":810345600000,
    "smoothed_cost_price":1.0942756744,
    "STORE":44,
    "UPC":1660051312
  },
  {
    "date_start":810432000000,
    "date_end":810950400000,
    "smoothed_cost_price":1.0544213699,
    "STORE":122,
    "UPC":1660051312
  },
  {
    "date_start":811036800000,
    "date_end":811555200000,
    "smoothed_cost_price":1.0710532875,
    "STORE":32,
    "UPC":1660051312
  },
  {
    "date_start":811641600000,
    "date_end":812160000000,
    "smoothed_cost_price":1.0890612353,
    "STORE":93,
    "UPC":1660051312
  },
  {
    "date_start":812246400000,
    "date_end":812764800000,
    "smoothed_cost_price":1.0501550107,
    "STORE":105,
    "UPC":1660051312
  },
  {
    "date_start":812851200000,
    "date_end":813369600000,
    "smoothed_cost_price":1.0658194052,
    "STORE":98,
    "UPC":1660051312
  },
  {
    "date_start":813456000000,
    "date_end":813974400000,
    "smoothed_cost_price":1.0830489123,
    "STORE":109,
    "UPC":1660051312
  },
  {
    "date_start":814060800000,
    "date_end":814579200000,
    "smoothed_cost_price":1.0634138374,
    "STORE":122,
    "UPC":1660051312
  },
  {
    "date_start":814665600000,
    "date_end":815184000000,
    "smoothed_cost_price":1.047348776,
    "STORE":132,
    "UPC":1660051312
  },
  {
    "date_start":815270400000,
    "date_end":815788800000,
    "smoothed_cost_price":1.0339957031,
    "STORE":93,
    "UPC":1660051312
  },
  {
    "date_start":815875200000,
    "date_end":816393600000,
    "smoothed_cost_price":1.0219416965,
    "STORE":121,
    "UPC":1660051312
  },
  {
    "date_start":816480000000,
    "date_end":816998400000,
    "smoothed_cost_price":1.0117125547,
    "STORE":76,
    "UPC":1660051312
  },
  {
    "date_start":817084800000,
    "date_end":817603200000,
    "smoothed_cost_price":1.0299713629,
    "STORE":80,
    "UPC":1660051312
  },
  {
    "date_start":817689600000,
    "date_end":818208000000,
    "smoothed_cost_price":1.0212258348,
    "STORE":128,
    "UPC":1660051312
  },
  {
    "date_start":818294400000,
    "date_end":818812800000,
    "smoothed_cost_price":1.0121603876,
    "STORE":76,
    "UPC":1660051312
  },
  {
    "date_start":818899200000,
    "date_end":819417600000,
    "smoothed_cost_price":1.0054141353,
    "STORE":130,
    "UPC":1660051312
  },
  {
    "date_start":819504000000,
    "date_end":820022400000,
    "smoothed_cost_price":0.9841072319,
    "STORE":137,
    "UPC":1660051312
  },
  {
    "date_start":820108800000,
    "date_end":820627200000,
    "smoothed_cost_price":0.9762300458,
    "STORE":137,
    "UPC":1660051312
  },
  {
    "date_start":820713600000,
    "date_end":821232000000,
    "smoothed_cost_price":0.9727114693,
    "STORE":113,
    "UPC":1660051312
  },
  {
    "date_start":821318400000,
    "date_end":821836800000,
    "smoothed_cost_price":0.9728860279,
    "STORE":121,
    "UPC":1660051312
  },
  {
    "date_start":821923200000,
    "date_end":822441600000,
    "smoothed_cost_price":0.9730596062,
    "STORE":113,
    "UPC":1660051312
  },
  {
    "date_start":822528000000,
    "date_end":823046400000,
    "smoothed_cost_price":0.9733366929,
    "STORE":137,
    "UPC":1660051312
  },
  {
    "date_start":823132800000,
    "date_end":823651200000,
    "smoothed_cost_price":0.9736492942,
    "STORE":98,
    "UPC":1660051312
  },
  {
    "date_start":823737600000,
    "date_end":824256000000,
    "smoothed_cost_price":0.9739050589,
    "STORE":18,
    "UPC":1660051312
  },
  {
    "date_start":824342400000,
    "date_end":824860800000,
    "smoothed_cost_price":0.9741143209,
    "STORE":122,
    "UPC":1660051312
  },
  {
    "date_start":824947200000,
    "date_end":825465600000,
    "smoothed_cost_price":1.0097475353,
    "STORE":18,
    "UPC":1660051312
  },
  {
    "date_start":825552000000,
    "date_end":826070400000,
    "smoothed_cost_price":1.0389019834,
    "STORE":107,
    "UPC":1660051312
  },
  {
    "date_start":826156800000,
    "date_end":826675200000,
    "smoothed_cost_price":1.0272936228,
    "STORE":113,
    "UPC":1660051312
  },
  {
    "date_start":826761600000,
    "date_end":827280000000,
    "smoothed_cost_price":1.0177958732,
    "STORE":12,
    "UPC":1660051312
  },
  {
    "date_start":827366400000,
    "date_end":827884800000,
    "smoothed_cost_price":1.0454869872,
    "STORE":32,
    "UPC":1660051312
  },
  {
    "date_start":827971200000,
    "date_end":828489600000,
    "smoothed_cost_price":1.0325426031,
    "STORE":18,
    "UPC":1660051312
  },
  {
    "date_start":828576000000,
    "date_end":829094400000,
    "smoothed_cost_price":1.057311751,
    "STORE":109,
    "UPC":1660051312
  },
  {
    "date_start":829180800000,
    "date_end":829699200000,
    "smoothed_cost_price":1.0725659099,
    "STORE":113,
    "UPC":1660051312
  },
  {
    "date_start":829785600000,
    "date_end":830304000000,
    "smoothed_cost_price":1.0390948657,
    "STORE":80,
    "UPC":1660051312
  },
  {
    "date_start":830390400000,
    "date_end":830908800000,
    "smoothed_cost_price":1.0119451023,
    "STORE":32,
    "UPC":1660051312
  },
  {
    "date_start":830995200000,
    "date_end":831513600000,
    "smoothed_cost_price":1.0359427276,
    "STORE":109,
    "UPC":1660051312
  },
  {
    "date_start":831600000000,
    "date_end":832118400000,
    "smoothed_cost_price":1.0565652014,
    "STORE":128,
    "UPC":1660051312
  },
  {
    "date_start":832204800000,
    "date_end":832723200000,
    "smoothed_cost_price":1.0279693845,
    "STORE":98,
    "UPC":1660051312
  },
  {
    "date_start":832809600000,
    "date_end":833328000000,
    "smoothed_cost_price":1.0091976479,
    "STORE":130,
    "UPC":1660051312
  },
  {
    "date_start":833414400000,
    "date_end":833932800000,
    "smoothed_cost_price":1.0352824392,
    "STORE":32,
    "UPC":1660051312
  },
  {
    "date_start":834019200000,
    "date_end":834537600000,
    "smoothed_cost_price":0.9953516775,
    "STORE":98,
    "UPC":1660051312
  },
  {
    "date_start":834624000000,
    "date_end":835142400000,
    "smoothed_cost_price":0.9580417361,
    "STORE":114,
    "UPC":1660051312
  },
  {
    "date_start":835228800000,
    "date_end":835747200000,
    "smoothed_cost_price":0.9471495568,
    "STORE":44,
    "UPC":1660051312
  },
  {
    "date_start":835833600000,
    "date_end":836352000000,
    "smoothed_cost_price":0.9876854556,
    "STORE":12,
    "UPC":1660051312
  },
  {
    "date_start":836438400000,
    "date_end":836956800000,
    "smoothed_cost_price":1.0208511909,
    "STORE":130,
    "UPC":1660051312
  },
  {
    "date_start":837043200000,
    "date_end":837561600000,
    "smoothed_cost_price":1.0479867926,
    "STORE":32,
    "UPC":1660051312
  },
  {
    "date_start":837648000000,
    "date_end":838166400000,
    "smoothed_cost_price":1.0347222924,
    "STORE":124,
    "UPC":1660051312
  },
  {
    "date_start":838252800000,
    "date_end":838771200000,
    "smoothed_cost_price":1.0567498226,
    "STORE":113,
    "UPC":1660051312
  },
  {
    "date_start":838857600000,
    "date_end":839376000000,
    "smoothed_cost_price":1.0773584003,
    "STORE":105,
    "UPC":1660051312
  },
  {
    "date_start":839462400000,
    "date_end":839980800000,
    "smoothed_cost_price":1.0942199639,
    "STORE":107,
    "UPC":1660051312
  },
  {
    "date_start":840067200000,
    "date_end":840585600000,
    "smoothed_cost_price":1.038651425,
    "STORE":132,
    "UPC":1660051312
  },
  {
    "date_start":840672000000,
    "date_end":841190400000,
    "smoothed_cost_price":1.0090877114,
    "STORE":113,
    "UPC":1660051312
  },
  {
    "date_start":841276800000,
    "date_end":841795200000,
    "smoothed_cost_price":0.9865355744,
    "STORE":105,
    "UPC":1660051312
  },
  {
    "date_start":841881600000,
    "date_end":842400000000,
    "smoothed_cost_price":0.9822007276,
    "STORE":128,
    "UPC":1660051312
  },
  {
    "date_start":842486400000,
    "date_end":843004800000,
    "smoothed_cost_price":0.9584283529,
    "STORE":132,
    "UPC":1660051312
  },
  {
    "date_start":843091200000,
    "date_end":843609600000,
    "smoothed_cost_price":0.939008713,
    "STORE":111,
    "UPC":1660051312
  },
  {
    "date_start":843696000000,
    "date_end":844214400000,
    "smoothed_cost_price":0.9299562727,
    "STORE":98,
    "UPC":1660051312
  },
  {
    "date_start":844300800000,
    "date_end":844819200000,
    "smoothed_cost_price":0.9220487686,
    "STORE":98,
    "UPC":1660051312
  },
  {
    "date_start":844905600000,
    "date_end":845424000000,
    "smoothed_cost_price":0.9155933561,
    "STORE":122,
    "UPC":1660051312
  },
  {
    "date_start":845510400000,
    "date_end":846028800000,
    "smoothed_cost_price":0.9372317383,
    "STORE":12,
    "UPC":1660051312
  },
  {
    "date_start":846115200000,
    "date_end":846633600000,
    "smoothed_cost_price":0.9795798162,
    "STORE":100,
    "UPC":1660051312
  },
  {
    "date_start":846720000000,
    "date_end":847238400000,
    "smoothed_cost_price":1.0142282436,
    "STORE":114,
    "UPC":1660051312
  },
  {
    "date_start":847324800000,
    "date_end":847843200000,
    "smoothed_cost_price":1.0425769569,
    "STORE":128,
    "UPC":1660051312
  },
  {
    "date_start":847929600000,
    "date_end":848448000000,
    "smoothed_cost_price":1.0146998283,
    "STORE":93,
    "UPC":1660051312
  },
  {
    "date_start":848534400000,
    "date_end":849052800000,
    "smoothed_cost_price":1.0284558482,
    "STORE":113,
    "UPC":1660051312
  },
  {
    "date_start":849139200000,
    "date_end":849657600000,
    "smoothed_cost_price":1.0032479743,
    "STORE":107,
    "UPC":1660051312
  },
  {
    "date_start":849744000000,
    "date_end":850262400000,
    "smoothed_cost_price":1.0278607896,
    "STORE":128,
    "UPC":1660051312
  },
  {
    "date_start":850348800000,
    "date_end":850867200000,
    "smoothed_cost_price":1.0087668581,
    "STORE":109,
    "UPC":1660051312
  },
  {
    "date_start":850953600000,
    "date_end":851472000000,
    "smoothed_cost_price":0.966894846,
    "STORE":111,
    "UPC":1660051312
  },
  {
    "date_start":851558400000,
    "date_end":852076800000,
    "smoothed_cost_price":0.9554955331,
    "STORE":44,
    "UPC":1660051312
  },
  {
    "date_start":852163200000,
    "date_end":852681600000,
    "smoothed_cost_price":0.994522921,
    "STORE":12,
    "UPC":1660051312
  },
  {
    "date_start":852768000000,
    "date_end":853286400000,
    "smoothed_cost_price":1.0264544202,
    "STORE":76,
    "UPC":1660051312
  },
  {
    "date_start":853372800000,
    "date_end":853891200000,
    "smoothed_cost_price":1.0525801923,
    "STORE":105,
    "UPC":1660051312
  },
  {
    "date_start":853977600000,
    "date_end":854496000000,
    "smoothed_cost_price":1.073955824,
    "STORE":122,
    "UPC":1660051312
  },
  {
    "date_start":854582400000,
    "date_end":855100800000,
    "smoothed_cost_price":1.08600575,
    "STORE":130,
    "UPC":1660051312
  },
  {
    "date_start":855187200000,
    "date_end":855705600000,
    "smoothed_cost_price":1.0503907954,
    "STORE":109,
    "UPC":1660051312
  },
  {
    "date_start":855792000000,
    "date_end":856310400000,
    "smoothed_cost_price":1.0676727872,
    "STORE":113,
    "UPC":1660051312
  },
  {
    "date_start":856396800000,
    "date_end":856915200000,
    "smoothed_cost_price":1.0818125986,
    "STORE":44,
    "UPC":1660051312
  },
  {
    "date_start":857001600000,
    "date_end":857520000000,
    "smoothed_cost_price":1.0447782852,
    "STORE":98,
    "UPC":1660051312
  },
  {
    "date_start":857606400000,
    "date_end":858124800000,
    "smoothed_cost_price":1.0674573243,
    "STORE":113,
    "UPC":1660051312
  },
  {
    "date_start":858211200000,
    "date_end":858729600000,
    "smoothed_cost_price":1.0861280229,
    "STORE":122,
    "UPC":1660051312
  },
  {
    "date_start":858816000000,
    "date_end":859334400000,
    "smoothed_cost_price":1.0371490263,
    "STORE":105,
    "UPC":1660051312
  },
  {
    "date_start":859420800000,
    "date_end":859939200000,
    "smoothed_cost_price":1.0052875291,
    "STORE":100,
    "UPC":1660051312
  },
  {
    "date_start":860025600000,
    "date_end":860544000000,
    "smoothed_cost_price":0.9792190314,
    "STORE":122,
    "UPC":1660051312
  },
  {
    "date_start":860630400000,
    "date_end":861148800000,
    "smoothed_cost_price":1.0100007832,
    "STORE":98,
    "UPC":1660051312
  },
  {
    "date_start":861235200000,
    "date_end":861753600000,
    "smoothed_cost_price":1.003458103,
    "STORE":74,
    "UPC":1660051312
  },
  {
    "date_start":861840000000,
    "date_end":862358400000,
    "smoothed_cost_price":1.0336501676,
    "STORE":76,
    "UPC":1660051312
  },
  {
    "date_start":862444800000,
    "date_end":862963200000,
    "smoothed_cost_price":1.0531292962,
    "STORE":124,
    "UPC":1660051312
  }
]