[
  {
    "date_start":621734400000,
    "date_end":622252800000,
    "smoothed_cost_price":0.79101,
    "STORE":104,
    "UPC":7020211703
  },
  {
    "date_start":622339200000,
    "date_end":622857600000,
    "smoothed_cost_price":0.79101,
    "STORE":104,
    "UPC":7020211703
  },
  {
    "date_start":622944000000,
    "date_end":623462400000,
    "smoothed_cost_price":0.79101,
    "STORE":104,
    "UPC":7020211703
  },
  {
    "date_start":623548800000,
    "date_end":624067200000,
    "smoothed_cost_price":0.7910127273,
    "STORE":104,
    "UPC":7020211703
  },
  {
    "date_start":624153600000,
    "date_end":624672000000,
    "smoothed_cost_price":0.7910122314,
    "STORE":104,
    "UPC":7020211703
  },
  {
    "date_start":624758400000,
    "date_end":625276800000,
    "smoothed_cost_price":0.7910118257,
    "STORE":104,
    "UPC":7020211703
  },
  {
    "date_start":625363200000,
    "date_end":625881600000,
    "smoothed_cost_price":0.7910114938,
    "STORE":104,
    "UPC":7020211703
  },
  {
    "date_start":625968000000,
    "date_end":626486400000,
    "smoothed_cost_price":0.7910112222,
    "STORE":104,
    "UPC":7020211703
  },
  {
    "date_start":626572800000,
    "date_end":627091200000,
    "smoothed_cost_price":0.7910109999,
    "STORE":104,
    "UPC":7020211703
  },
  {
    "date_start":627177600000,
    "date_end":627696000000,
    "smoothed_cost_price":0.7910108181,
    "STORE":104,
    "UPC":7020211703
  },
  {
    "date_start":627782400000,
    "date_end":628300800000,
    "smoothed_cost_price":0.7910106694,
    "STORE":104,
    "UPC":7020211703
  },
  {
    "date_start":628387200000,
    "date_end":628905600000,
    "smoothed_cost_price":0.7910105477,
    "STORE":104,
    "UPC":7020211703
  },
  {
    "date_start":628992000000,
    "date_end":629510400000,
    "smoothed_cost_price":0.7910124481,
    "STORE":104,
    "UPC":7020211703
  },
  {
    "date_start":629596800000,
    "date_end":630115200000,
    "smoothed_cost_price":0.791016003,
    "STORE":104,
    "UPC":7020211703
  },
  {
    "date_start":630201600000,
    "date_end":630720000000,
    "smoothed_cost_price":0.7910189115,
    "STORE":104,
    "UPC":7020211703
  },
  {
    "date_start":630806400000,
    "date_end":631324800000,
    "smoothed_cost_price":0.7910212913,
    "STORE":104,
    "UPC":7020211703
  },
  {
    "date_start":631411200000,
    "date_end":631929600000,
    "smoothed_cost_price":0.7910219656,
    "STORE":104,
    "UPC":7020211703
  },
  {
    "date_start":632016000000,
    "date_end":632534400000,
    "smoothed_cost_price":0.7910225173,
    "STORE":104,
    "UPC":7020211703
  },
  {
    "date_start":632620800000,
    "date_end":633139200000,
    "smoothed_cost_price":0.7910229687,
    "STORE":104,
    "UPC":7020211703
  },
  {
    "date_start":633225600000,
    "date_end":633744000000,
    "smoothed_cost_price":0.791023338,
    "STORE":104,
    "UPC":7020211703
  },
  {
    "date_start":633830400000,
    "date_end":634348800000,
    "smoothed_cost_price":0.7542889129,
    "STORE":104,
    "UPC":7020211703
  },
  {
    "date_start":634435200000,
    "date_end":634953600000,
    "smoothed_cost_price":0.7609682015,
    "STORE":104,
    "UPC":7020211703
  },
  {
    "date_start":635040000000,
    "date_end":635558400000,
    "smoothed_cost_price":0.7664330739,
    "STORE":104,
    "UPC":7020211703
  },
  {
    "date_start":635644800000,
    "date_end":636163200000,
    "smoothed_cost_price":0.7709048787,
    "STORE":104,
    "UPC":7020211703
  },
  {
    "date_start":636249600000,
    "date_end":636768000000,
    "smoothed_cost_price":0.7745630826,
    "STORE":104,
    "UPC":7020211703
  },
  {
    "date_start":636854400000,
    "date_end":637372800000,
    "smoothed_cost_price":0.7775534312,
    "STORE":104,
    "UPC":7020211703
  },
  {
    "date_start":637459200000,
    "date_end":637977600000,
    "smoothed_cost_price":0.7800028073,
    "STORE":104,
    "UPC":7020211703
  },
  {
    "date_start":638064000000,
    "date_end":638582400000,
    "smoothed_cost_price":0.7820068424,
    "STORE":104,
    "UPC":7020211703
  },
  {
    "date_start":638668800000,
    "date_end":639187200000,
    "smoothed_cost_price":0.7836465074,
    "STORE":104,
    "UPC":7020211703
  },
  {
    "date_start":639273600000,
    "date_end":639792000000,
    "smoothed_cost_price":0.842794597,
    "STORE":104,
    "UPC":7020211703
  },
  {
    "date_start":639878400000,
    "date_end":640396800000,
    "smoothed_cost_price":0.9206584884,
    "STORE":104,
    "UPC":7020211703
  },
  {
    "date_start":640483200000,
    "date_end":641001600000,
    "smoothed_cost_price":0.9843653087,
    "STORE":104,
    "UPC":7020211703
  },
  {
    "date_start":641088000000,
    "date_end":641606400000,
    "smoothed_cost_price":1.0364890708,
    "STORE":104,
    "UPC":7020211703
  },
  {
    "date_start":641692800000,
    "date_end":642211200000,
    "smoothed_cost_price":1.0791357852,
    "STORE":104,
    "UPC":7020211703
  },
  {
    "date_start":642297600000,
    "date_end":642816000000,
    "smoothed_cost_price":1.1140285515,
    "STORE":104,
    "UPC":7020211703
  },
  {
    "date_start":642902400000,
    "date_end":643420800000,
    "smoothed_cost_price":1.1425771785,
    "STORE":104,
    "UPC":7020211703
  },
  {
    "date_start":643507200000,
    "date_end":644025600000,
    "smoothed_cost_price":1.136465146,
    "STORE":104,
    "UPC":7020211703
  },
  {
    "date_start":644112000000,
    "date_end":644630400000,
    "smoothed_cost_price":1.1609343922,
    "STORE":104,
    "UPC":7020211703
  },
  {
    "date_start":644716800000,
    "date_end":645235200000,
    "smoothed_cost_price":1.1809546845,
    "STORE":104,
    "UPC":7020211703
  },
  {
    "date_start":645321600000,
    "date_end":645840000000,
    "smoothed_cost_price":1.1678649237,
    "STORE":104,
    "UPC":7020211703
  },
  {
    "date_start":645926400000,
    "date_end":646444800000,
    "smoothed_cost_price":1.1866251194,
    "STORE":104,
    "UPC":7020211703
  },
  {
    "date_start":646531200000,
    "date_end":647049600000,
    "smoothed_cost_price":1.1725043704,
    "STORE":104,
    "UPC":7020211703
  },
  {
    "date_start":647136000000,
    "date_end":647654400000,
    "smoothed_cost_price":1.1904210303,
    "STORE":104,
    "UPC":7020211703
  },
  {
    "date_start":647740800000,
    "date_end":648259200000,
    "smoothed_cost_price":1.2050801157,
    "STORE":104,
    "UPC":7020211703
  },
  {
    "date_start":648345600000,
    "date_end":648864000000,
    "smoothed_cost_price":1.2170739129,
    "STORE":104,
    "UPC":7020211703
  },
  {
    "date_start":648950400000,
    "date_end":649468800000,
    "smoothed_cost_price":1.1247037469,
    "STORE":104,
    "UPC":7020211703
  },
  {
    "date_start":649555200000,
    "date_end":650073600000,
    "smoothed_cost_price":1.0640321566,
    "STORE":104,
    "UPC":7020211703
  },
  {
    "date_start":650160000000,
    "date_end":650678400000,
    "smoothed_cost_price":1.0143917645,
    "STORE":104,
    "UPC":7020211703
  },
  {
    "date_start":650764800000,
    "date_end":651283200000,
    "smoothed_cost_price":1.0610545346,
    "STORE":104,
    "UPC":7020211703
  },
  {
    "date_start":651369600000,
    "date_end":651888000000,
    "smoothed_cost_price":1.099234801,
    "STORE":104,
    "UPC":7020211703
  },
  {
    "date_start":651974400000,
    "date_end":652492800000,
    "smoothed_cost_price":1.1010032008,
    "STORE":104,
    "UPC":7020211703
  },
  {
    "date_start":652579200000,
    "date_end":653097600000,
    "smoothed_cost_price":1.1319200734,
    "STORE":104,
    "UPC":7020211703
  },
  {
    "date_start":653184000000,
    "date_end":653702400000,
    "smoothed_cost_price":1.1206706055,
    "STORE":104,
    "UPC":7020211703
  },
  {
    "date_start":653788800000,
    "date_end":654307200000,
    "smoothed_cost_price":1.1114704954,
    "STORE":104,
    "UPC":7020211703
  },
  {
    "date_start":654393600000,
    "date_end":654912000000,
    "smoothed_cost_price":1.1039391326,
    "STORE":104,
    "UPC":7020211703
  },
  {
    "date_start":654998400000,
    "date_end":655516800000,
    "smoothed_cost_price":1.0977780176,
    "STORE":104,
    "UPC":7020211703
  },
  {
    "date_start":655603200000,
    "date_end":656121600000,
    "smoothed_cost_price":1.0927401962,
    "STORE":104,
    "UPC":7020211703
  },
  {
    "date_start":656208000000,
    "date_end":656726400000,
    "smoothed_cost_price":1.0886143424,
    "STORE":104,
    "UPC":7020211703
  },
  {
    "date_start":656812800000,
    "date_end":657331200000,
    "smoothed_cost_price":1.0561404619,
    "STORE":104,
    "UPC":7020211703
  },
  {
    "date_start":657417600000,
    "date_end":657936000000,
    "smoothed_cost_price":1.0295709234,
    "STORE":104,
    "UPC":7020211703
  },
  {
    "date_start":658022400000,
    "date_end":658540800000,
    "smoothed_cost_price":1.00783221,
    "STORE":104,
    "UPC":7020211703
  },
  {
    "date_start":658627200000,
    "date_end":659145600000,
    "smoothed_cost_price":0.99004599,
    "STORE":104,
    "UPC":7020211703
  },
  {
    "date_start":659232000000,
    "date_end":659750400000,
    "smoothed_cost_price":0.9754936282,
    "STORE":104,
    "UPC":7020211703
  },
  {
    "date_start":659836800000,
    "date_end":660355200000,
    "smoothed_cost_price":0.9635871504,
    "STORE":104,
    "UPC":7020211703
  },
  {
    "date_start":660441600000,
    "date_end":660960000000,
    "smoothed_cost_price":0.9538454867,
    "STORE":104,
    "UPC":7020211703
  },
  {
    "date_start":661046400000,
    "date_end":661564800000,
    "smoothed_cost_price":0.9458750345,
    "STORE":104,
    "UPC":7020211703
  },
  {
    "date_start":661651200000,
    "date_end":662169600000,
    "smoothed_cost_price":0.9393537555,
    "STORE":104,
    "UPC":7020211703
  },
  {
    "date_start":662256000000,
    "date_end":662774400000,
    "smoothed_cost_price":0.9340181636,
    "STORE":104,
    "UPC":7020211703
  },
  {
    "date_start":662860800000,
    "date_end":663379200000,
    "smoothed_cost_price":0.9296526793,
    "STORE":104,
    "UPC":7020211703
  },
  {
    "date_start":663465600000,
    "date_end":663984000000,
    "smoothed_cost_price":0.9260809194,
    "STORE":104,
    "UPC":7020211703
  },
  {
    "date_start":664070400000,
    "date_end":664588800000,
    "smoothed_cost_price":0.9231585705,
    "STORE":104,
    "UPC":7020211703
  },
  {
    "date_start":664675200000,
    "date_end":665193600000,
    "smoothed_cost_price":0.9207675576,
    "STORE":104,
    "UPC":7020211703
  },
  {
    "date_start":665280000000,
    "date_end":665798400000,
    "smoothed_cost_price":0.9188112744,
    "STORE":104,
    "UPC":7020211703
  },
  {
    "date_start":665884800000,
    "date_end":666403200000,
    "smoothed_cost_price":0.8953903154,
    "STORE":104,
    "UPC":7020211703
  },
  {
    "date_start":666489600000,
    "date_end":667008000000,
    "smoothed_cost_price":0.876241349,
    "STORE":104,
    "UPC":7020211703
  },
  {
    "date_start":667094400000,
    "date_end":667612800000,
    "smoothed_cost_price":0.8605647401,
    "STORE":104,
    "UPC":7020211703
  },
  {
    "date_start":667699200000,
    "date_end":668217600000,
    "smoothed_cost_price":0.8477384237,
    "STORE":104,
    "UPC":7020211703
  },
  {
    "date_start":668304000000,
    "date_end":668822400000,
    "smoothed_cost_price":0.8372441649,
    "STORE":104,
    "UPC":7020211703
  },
  {
    "date_start":668908800000,
    "date_end":669427200000,
    "smoothed_cost_price":0.8286579531,
    "STORE":104,
    "UPC":7020211703
  },
  {
    "date_start":669513600000,
    "date_end":670032000000,
    "smoothed_cost_price":0.8216328707,
    "STORE":104,
    "UPC":7020211703
  },
  {
    "date_start":670118400000,
    "date_end":670636800000,
    "smoothed_cost_price":0.815885076,
    "STORE":104,
    "UPC":7020211703
  },
  {
    "date_start":670723200000,
    "date_end":671241600000,
    "smoothed_cost_price":0.8111823349,
    "STORE":104,
    "UPC":7020211703
  },
  {
    "date_start":671328000000,
    "date_end":671846400000,
    "smoothed_cost_price":0.8073346377,
    "STORE":104,
    "UPC":7020211703
  },
  {
    "date_start":671932800000,
    "date_end":672451200000,
    "smoothed_cost_price":0.8041865217,
    "STORE":104,
    "UPC":7020211703
  },
  {
    "date_start":672537600000,
    "date_end":673056000000,
    "smoothed_cost_price":0.8016107905,
    "STORE":104,
    "UPC":7020211703
  },
  {
    "date_start":673142400000,
    "date_end":673660800000,
    "smoothed_cost_price":0.799503374,
    "STORE":104,
    "UPC":7020211703
  },
  {
    "date_start":673747200000,
    "date_end":674265600000,
    "smoothed_cost_price":0.7977791242,
    "STORE":104,
    "UPC":7020211703
  },
  {
    "date_start":674352000000,
    "date_end":674870400000,
    "smoothed_cost_price":0.7963683744,
    "STORE":104,
    "UPC":7020211703
  },
  {
    "date_start":674956800000,
    "date_end":675475200000,
    "smoothed_cost_price":0.7952141245,
    "STORE":104,
    "UPC":7020211703
  },
  {
    "date_start":675561600000,
    "date_end":676080000000,
    "smoothed_cost_price":0.7942697382,
    "STORE":104,
    "UPC":7020211703
  },
  {
    "date_start":676166400000,
    "date_end":676684800000,
    "smoothed_cost_price":0.7935063313,
    "STORE":104,
    "UPC":7020211703
  },
  {
    "date_start":676771200000,
    "date_end":677289600000,
    "smoothed_cost_price":0.7928724529,
    "STORE":104,
    "UPC":7020211703
  },
  {
    "date_start":677376000000,
    "date_end":677894400000,
    "smoothed_cost_price":0.7923538251,
    "STORE":104,
    "UPC":7020211703
  },
  {
    "date_start":677980800000,
    "date_end":678499200000,
    "smoothed_cost_price":0.7919294932,
    "STORE":104,
    "UPC":7020211703
  },
  {
    "date_start":678585600000,
    "date_end":679104000000,
    "smoothed_cost_price":0.7915823126,
    "STORE":104,
    "UPC":7020211703
  },
  {
    "date_start":679190400000,
    "date_end":679708800000,
    "smoothed_cost_price":0.7912982558,
    "STORE":104,
    "UPC":7020211703
  },
  {
    "date_start":679795200000,
    "date_end":680313600000,
    "smoothed_cost_price":0.7910658457,
    "STORE":104,
    "UPC":7020211703
  },
  {
    "date_start":680400000000,
    "date_end":680918400000,
    "smoothed_cost_price":0.7908655101,
    "STORE":104,
    "UPC":7020211703
  },
  {
    "date_start":681004800000,
    "date_end":681523200000,
    "smoothed_cost_price":0.790707781,
    "STORE":104,
    "UPC":7020211703
  },
  {
    "date_start":681609600000,
    "date_end":682128000000,
    "smoothed_cost_price":0.7905787299,
    "STORE":104,
    "UPC":7020211703
  },
  {
    "date_start":682214400000,
    "date_end":682732800000,
    "smoothed_cost_price":0.7468451426,
    "STORE":104,
    "UPC":7020211703
  },
  {
    "date_start":682819200000,
    "date_end":683337600000,
    "smoothed_cost_price":0.7110631167,
    "STORE":104,
    "UPC":7020211703
  },
  {
    "date_start":683424000000,
    "date_end":683942400000,
    "smoothed_cost_price":0.6817869137,
    "STORE":104,
    "UPC":7020211703
  },
  {
    "date_start":684028800000,
    "date_end":684547200000,
    "smoothed_cost_price":0.6578336566,
    "STORE":104,
    "UPC":7020211703
  },
  {
    "date_start":684633600000,
    "date_end":685152000000,
    "smoothed_cost_price":0.6382355372,
    "STORE":104,
    "UPC":7020211703
  },
  {
    "date_start":685238400000,
    "date_end":685756800000,
    "smoothed_cost_price":0.6222007123,
    "STORE":104,
    "UPC":7020211703
  },
  {
    "date_start":685843200000,
    "date_end":686361600000,
    "smoothed_cost_price":0.6090813101,
    "STORE":104,
    "UPC":7020211703
  },
  {
    "date_start":686448000000,
    "date_end":686966400000,
    "smoothed_cost_price":0.5983472537,
    "STORE":104,
    "UPC":7020211703
  },
  {
    "date_start":687052800000,
    "date_end":687571200000,
    "smoothed_cost_price":0.5895648439,
    "STORE":104,
    "UPC":7020211703
  },
  {
    "date_start":687657600000,
    "date_end":688176000000,
    "smoothed_cost_price":0.5823792359,
    "STORE":104,
    "UPC":7020211703
  },
  {
    "date_start":688262400000,
    "date_end":688780800000,
    "smoothed_cost_price":0.5765001021,
    "STORE":104,
    "UPC":7020211703
  },
  {
    "date_start":688867200000,
    "date_end":689385600000,
    "smoothed_cost_price":0.5716899017,
    "STORE":104,
    "UPC":7020211703
  },
  {
    "date_start":689472000000,
    "date_end":689990400000,
    "smoothed_cost_price":0.5313893742,
    "STORE":104,
    "UPC":7020211703
  },
  {
    "date_start":690076800000,
    "date_end":690595200000,
    "smoothed_cost_price":0.5347811243,
    "STORE":104,
    "UPC":7020211703
  },
  {
    "date_start":690681600000,
    "date_end":691200000000,
    "smoothed_cost_price":0.5375561926,
    "STORE":104,
    "UPC":7020211703
  },
  {
    "date_start":691286400000,
    "date_end":691804800000,
    "smoothed_cost_price":0.503461794,
    "STORE":104,
    "UPC":7020211703
  },
  {
    "date_start":691891200000,
    "date_end":692409600000,
    "smoothed_cost_price":0.511931286,
    "STORE":104,
    "UPC":7020211703
  },
  {
    "date_start":692496000000,
    "date_end":693014400000,
    "smoothed_cost_price":0.4461294158,
    "STORE":104,
    "UPC":7020211703
  },
  {
    "date_start":693100800000,
    "date_end":693619200000,
    "smoothed_cost_price":0.4650229766,
    "STORE":104,
    "UPC":7020211703
  },
  {
    "date_start":693705600000,
    "date_end":694224000000,
    "smoothed_cost_price":0.4804813445,
    "STORE":104,
    "UPC":7020211703
  },
  {
    "date_start":694310400000,
    "date_end":694828800000,
    "smoothed_cost_price":0.4931291,
    "STORE":104,
    "UPC":7020211703
  },
  {
    "date_start":694915200000,
    "date_end":695433600000,
    "smoothed_cost_price":0.5034772636,
    "STORE":104,
    "UPC":7020211703
  },
  {
    "date_start":695520000000,
    "date_end":696038400000,
    "smoothed_cost_price":0.511943943,
    "STORE":104,
    "UPC":7020211703
  },
  {
    "date_start":696124800000,
    "date_end":696643200000,
    "smoothed_cost_price":0.5188712261,
    "STORE":104,
    "UPC":7020211703
  },
  {
    "date_start":696729600000,
    "date_end":697248000000,
    "smoothed_cost_price":0.4881740941,
    "STORE":104,
    "UPC":7020211703
  },
  {
    "date_start":697334400000,
    "date_end":697852800000,
    "smoothed_cost_price":0.4994231679,
    "STORE":104,
    "UPC":7020211703
  },
  {
    "date_start":697939200000,
    "date_end":698457600000,
    "smoothed_cost_price":0.4722620464,
    "STORE":104,
    "UPC":7020211703
  },
  {
    "date_start":698544000000,
    "date_end":699062400000,
    "smoothed_cost_price":0.4864042198,
    "STORE":104,
    "UPC":7020211703
  },
  {
    "date_start":699148800000,
    "date_end":699667200000,
    "smoothed_cost_price":0.4979750889,
    "STORE":104,
    "UPC":7020211703
  },
  {
    "date_start":699753600000,
    "date_end":700272000000,
    "smoothed_cost_price":0.5074421637,
    "STORE":104,
    "UPC":7020211703
  },
  {
    "date_start":700358400000,
    "date_end":700876800000,
    "smoothed_cost_price":0.5151879521,
    "STORE":104,
    "UPC":7020211703
  },
  {
    "date_start":700963200000,
    "date_end":701481600000,
    "smoothed_cost_price":0.4851605063,
    "STORE":104,
    "UPC":7020211703
  },
  {
    "date_start":701568000000,
    "date_end":702086400000,
    "smoothed_cost_price":0.4969575051,
    "STORE":104,
    "UPC":7020211703
  },
  {
    "date_start":702172800000,
    "date_end":702691200000,
    "smoothed_cost_price":0.5066095951,
    "STORE":104,
    "UPC":7020211703
  },
  {
    "date_start":702777600000,
    "date_end":703296000000,
    "smoothed_cost_price":0.5145067596,
    "STORE":104,
    "UPC":7020211703
  },
  {
    "date_start":703382400000,
    "date_end":703900800000,
    "smoothed_cost_price":0.5209680761,
    "STORE":104,
    "UPC":7020211703
  },
  {
    "date_start":703987200000,
    "date_end":704505600000,
    "smoothed_cost_price":0.5262546077,
    "STORE":104,
    "UPC":7020211703
  },
  {
    "date_start":704592000000,
    "date_end":705110400000,
    "smoothed_cost_price":0.5305799517,
    "STORE":104,
    "UPC":7020211703
  },
  {
    "date_start":705196800000,
    "date_end":705715200000,
    "smoothed_cost_price":0.5341188696,
    "STORE":104,
    "UPC":7020211703
  },
  {
    "date_start":705801600000,
    "date_end":706320000000,
    "smoothed_cost_price":0.5370143479,
    "STORE":104,
    "UPC":7020211703
  },
  {
    "date_start":706406400000,
    "date_end":706924800000,
    "smoothed_cost_price":0.5393833755,
    "STORE":104,
    "UPC":7020211703
  },
  {
    "date_start":707011200000,
    "date_end":707529600000,
    "smoothed_cost_price":0.5413216709,
    "STORE":104,
    "UPC":7020211703
  },
  {
    "date_start":707616000000,
    "date_end":708134400000,
    "smoothed_cost_price":0.5429075489,
    "STORE":104,
    "UPC":7020211703
  },
  {
    "date_start":708220800000,
    "date_end":708739200000,
    "smoothed_cost_price":0.5442050855,
    "STORE":104,
    "UPC":7020211703
  },
  {
    "date_start":708825600000,
    "date_end":709344000000,
    "smoothed_cost_price":0.5452667063,
    "STORE":104,
    "UPC":7020211703
  },
  {
    "date_start":709430400000,
    "date_end":709948800000,
    "smoothed_cost_price":0.5461353051,
    "STORE":104,
    "UPC":7020211703
  },
  {
    "date_start":710035200000,
    "date_end":710553600000,
    "smoothed_cost_price":0.4741145224,
    "STORE":104,
    "UPC":7020211703
  },
  {
    "date_start":710640000000,
    "date_end":711158400000,
    "smoothed_cost_price":0.487919882,
    "STORE":104,
    "UPC":7020211703
  },
  {
    "date_start":711244800000,
    "date_end":711763200000,
    "smoothed_cost_price":0.659203358,
    "STORE":104,
    "UPC":7020211703
  },
  {
    "date_start":711849600000,
    "date_end":712368000000,
    "smoothed_cost_price":0.7993414747,
    "STORE":104,
    "UPC":7020211703
  },
  {
    "date_start":712454400000,
    "date_end":712972800000,
    "smoothed_cost_price":0.9139999338,
    "STORE":104,
    "UPC":7020211703
  },
  {
    "date_start":713059200000,
    "date_end":713577600000,
    "smoothed_cost_price":1.0078101277,
    "STORE":104,
    "UPC":7020211703
  },
  {
    "date_start":713664000000,
    "date_end":714182400000,
    "smoothed_cost_price":1.0845651954,
    "STORE":104,
    "UPC":7020211703
  },
  {
    "date_start":714268800000,
    "date_end":714787200000,
    "smoothed_cost_price":1.1473635235,
    "STORE":104,
    "UPC":7020211703
  },
  {
    "date_start":714873600000,
    "date_end":715392000000,
    "smoothed_cost_price":1.0823919738,
    "STORE":104,
    "UPC":7020211703
  },
  {
    "date_start":715478400000,
    "date_end":715996800000,
    "smoothed_cost_price":1.0292334331,
    "STORE":104,
    "UPC":7020211703
  },
  {
    "date_start":716083200000,
    "date_end":716601600000,
    "smoothed_cost_price":0.9857400816,
    "STORE":104,
    "UPC":7020211703
  },
  {
    "date_start":716688000000,
    "date_end":717206400000,
    "smoothed_cost_price":0.9501546122,
    "STORE":104,
    "UPC":7020211703
  },
  {
    "date_start":717292800000,
    "date_end":717811200000,
    "smoothed_cost_price":0.9210392282,
    "STORE":104,
    "UPC":7020211703
  },
  {
    "date_start":717897600000,
    "date_end":718416000000,
    "smoothed_cost_price":0.8972175503,
    "STORE":104,
    "UPC":7020211703
  },
  {
    "date_start":718502400000,
    "date_end":719020800000,
    "smoothed_cost_price":0.8777169048,
    "STORE":104,
    "UPC":7020211703
  },
  {
    "date_start":719107200000,
    "date_end":719625600000,
    "smoothed_cost_price":0.978124013,
    "STORE":104,
    "UPC":7020211703
  },
  {
    "date_start":719712000000,
    "date_end":720230400000,
    "smoothed_cost_price":0.9439232834,
    "STORE":104,
    "UPC":7020211703
  },
  {
    "date_start":720316800000,
    "date_end":720835200000,
    "smoothed_cost_price":0.9159408682,
    "STORE":104,
    "UPC":7020211703
  },
  {
    "date_start":720921600000,
    "date_end":721440000000,
    "smoothed_cost_price":0.8930461649,
    "STORE":104,
    "UPC":7020211703
  },
  {
    "date_start":721526400000,
    "date_end":722044800000,
    "smoothed_cost_price":0.8743141349,
    "STORE":104,
    "UPC":7020211703
  },
  {
    "date_start":722131200000,
    "date_end":722649600000,
    "smoothed_cost_price":0.8589879286,
    "STORE":104,
    "UPC":7020211703
  },
  {
    "date_start":722736000000,
    "date_end":723254400000,
    "smoothed_cost_price":0.8464483052,
    "STORE":104,
    "UPC":7020211703
  },
  {
    "date_start":723340800000,
    "date_end":723859200000,
    "smoothed_cost_price":0.8361886133,
    "STORE":104,
    "UPC":7020211703
  },
  {
    "date_start":723945600000,
    "date_end":724464000000,
    "smoothed_cost_price":0.82779432,
    "STORE":104,
    "UPC":7020211703
  },
  {
    "date_start":724550400000,
    "date_end":725068800000,
    "smoothed_cost_price":0.8209262618,
    "STORE":104,
    "UPC":7020211703
  },
  {
    "date_start":725155200000,
    "date_end":725673600000,
    "smoothed_cost_price":0.8153069415,
    "STORE":104,
    "UPC":7020211703
  },
  {
    "date_start":725760000000,
    "date_end":726278400000,
    "smoothed_cost_price":0.8107093158,
    "STORE":104,
    "UPC":7020211703
  },
  {
    "date_start":726364800000,
    "date_end":726883200000,
    "smoothed_cost_price":0.806947622,
    "STORE":104,
    "UPC":7020211703
  },
  {
    "date_start":726969600000,
    "date_end":727488000000,
    "smoothed_cost_price":0.8038698725,
    "STORE":104,
    "UPC":7020211703
  },
  {
    "date_start":727574400000,
    "date_end":728092800000,
    "smoothed_cost_price":0.8013517139,
    "STORE":104,
    "UPC":7020211703
  },
  {
    "date_start":728179200000,
    "date_end":728697600000,
    "smoothed_cost_price":0.7992914023,
    "STORE":104,
    "UPC":7020211703
  },
  {
    "date_start":728784000000,
    "date_end":729302400000,
    "smoothed_cost_price":0.7976056928,
    "STORE":104,
    "UPC":7020211703
  },
  {
    "date_start":729388800000,
    "date_end":729907200000,
    "smoothed_cost_price":0.7962264759,
    "STORE":104,
    "UPC":7020211703
  },
  {
    "date_start":729993600000,
    "date_end":730512000000,
    "smoothed_cost_price":0.7950980257,
    "STORE":104,
    "UPC":7020211703
  },
  {
    "date_start":730598400000,
    "date_end":731116800000,
    "smoothed_cost_price":0.7941747483,
    "STORE":104,
    "UPC":7020211703
  },
  {
    "date_start":731203200000,
    "date_end":731721600000,
    "smoothed_cost_price":0.7934193395,
    "STORE":104,
    "UPC":7020211703
  },
  {
    "date_start":731808000000,
    "date_end":732326400000,
    "smoothed_cost_price":0.7928012778,
    "STORE":104,
    "UPC":7020211703
  },
  {
    "date_start":732412800000,
    "date_end":732931200000,
    "smoothed_cost_price":0.7922955909,
    "STORE":104,
    "UPC":7020211703
  },
  {
    "date_start":733017600000,
    "date_end":733536000000,
    "smoothed_cost_price":0.7918818471,
    "STORE":104,
    "UPC":7020211703
  },
  {
    "date_start":733622400000,
    "date_end":734140800000,
    "smoothed_cost_price":0.7915433295,
    "STORE":104,
    "UPC":7020211703
  },
  {
    "date_start":734227200000,
    "date_end":734745600000,
    "smoothed_cost_price":0.7912663605,
    "STORE":104,
    "UPC":7020211703
  },
  {
    "date_start":734832000000,
    "date_end":735350400000,
    "smoothed_cost_price":0.7910397495,
    "STORE":104,
    "UPC":7020211703
  },
  {
    "date_start":735436800000,
    "date_end":735955200000,
    "smoothed_cost_price":0.7908543405,
    "STORE":104,
    "UPC":7020211703
  },
  {
    "date_start":736041600000,
    "date_end":736560000000,
    "smoothed_cost_price":0.7907026422,
    "STORE":104,
    "UPC":7020211703
  },
  {
    "date_start":736646400000,
    "date_end":737164800000,
    "smoothed_cost_price":0.7905785254,
    "STORE":104,
    "UPC":7020211703
  },
  {
    "date_start":737251200000,
    "date_end":737769600000,
    "smoothed_cost_price":0.7904769754,
    "STORE":104,
    "UPC":7020211703
  },
  {
    "date_start":737856000000,
    "date_end":738374400000,
    "smoothed_cost_price":0.7903938889,
    "STORE":104,
    "UPC":7020211703
  },
  {
    "date_start":738460800000,
    "date_end":738979200000,
    "smoothed_cost_price":0.7903259091,
    "STORE":104,
    "UPC":7020211703
  },
  {
    "date_start":739065600000,
    "date_end":739584000000,
    "smoothed_cost_price":0.7902702893,
    "STORE":104,
    "UPC":7020211703
  },
  {
    "date_start":739670400000,
    "date_end":740188800000,
    "smoothed_cost_price":0.7902247821,
    "STORE":104,
    "UPC":7020211703
  },
  {
    "date_start":740275200000,
    "date_end":740793600000,
    "smoothed_cost_price":0.790187549,
    "STORE":104,
    "UPC":7020211703
  },
  {
    "date_start":740880000000,
    "date_end":741398400000,
    "smoothed_cost_price":0.7901570856,
    "STORE":104,
    "UPC":7020211703
  },
  {
    "date_start":741484800000,
    "date_end":742003200000,
    "smoothed_cost_price":0.7901321609,
    "STORE":104,
    "UPC":7020211703
  },
  {
    "date_start":742089600000,
    "date_end":742608000000,
    "smoothed_cost_price":0.790111768,
    "STORE":104,
    "UPC":7020211703
  },
  {
    "date_start":742694400000,
    "date_end":743212800000,
    "smoothed_cost_price":0.7900950829,
    "STORE":104,
    "UPC":7020211703
  },
  {
    "date_start":743299200000,
    "date_end":743817600000,
    "smoothed_cost_price":0.7900814315,
    "STORE":104,
    "UPC":7020211703
  },
  {
    "date_start":743904000000,
    "date_end":744422400000,
    "smoothed_cost_price":0.7900702621,
    "STORE":104,
    "UPC":7020211703
  },
  {
    "date_start":744508800000,
    "date_end":745027200000,
    "smoothed_cost_price":0.7900611236,
    "STORE":104,
    "UPC":7020211703
  },
  {
    "date_start":745113600000,
    "date_end":745632000000,
    "smoothed_cost_price":0.7900536465,
    "STORE":104,
    "UPC":7020211703
  },
  {
    "date_start":745718400000,
    "date_end":746236800000,
    "smoothed_cost_price":0.790047529,
    "STORE":104,
    "UPC":7020211703
  },
  {
    "date_start":746323200000,
    "date_end":746841600000,
    "smoothed_cost_price":0.7900425237,
    "STORE":104,
    "UPC":7020211703
  },
  {
    "date_start":746928000000,
    "date_end":747446400000,
    "smoothed_cost_price":0.7900384285,
    "STORE":104,
    "UPC":7020211703
  },
  {
    "date_start":747532800000,
    "date_end":748051200000,
    "smoothed_cost_price":0.7900350779,
    "STORE":104,
    "UPC":7020211703
  },
  {
    "date_start":748137600000,
    "date_end":748656000000,
    "smoothed_cost_price":0.7900323364,
    "STORE":104,
    "UPC":7020211703
  },
  {
    "date_start":748742400000,
    "date_end":749260800000,
    "smoothed_cost_price":0.7900300934,
    "STORE":104,
    "UPC":7020211703
  },
  {
    "date_start":749347200000,
    "date_end":749865600000,
    "smoothed_cost_price":0.7900282583,
    "STORE":104,
    "UPC":7020211703
  },
  {
    "date_start":749952000000,
    "date_end":750470400000,
    "smoothed_cost_price":0.7900267568,
    "STORE":104,
    "UPC":7020211703
  },
  {
    "date_start":750556800000,
    "date_end":751075200000,
    "smoothed_cost_price":0.7900255283,
    "STORE":104,
    "UPC":7020211703
  },
  {
    "date_start":751161600000,
    "date_end":751680000000,
    "smoothed_cost_price":0.7900245231,
    "STORE":104,
    "UPC":7020211703
  },
  {
    "date_start":751766400000,
    "date_end":752284800000,
    "smoothed_cost_price":0.7900237007,
    "STORE":104,
    "UPC":7020211703
  },
  {
    "date_start":752371200000,
    "date_end":752889600000,
    "smoothed_cost_price":0.7900230279,
    "STORE":104,
    "UPC":7020211703
  },
  {
    "date_start":752976000000,
    "date_end":753494400000,
    "smoothed_cost_price":0.7900224774,
    "STORE":104,
    "UPC":7020211703
  },
  {
    "date_start":753580800000,
    "date_end":754099200000,
    "smoothed_cost_price":0.7900225724,
    "STORE":104,
    "UPC":7020211703
  },
  {
    "date_start":754185600000,
    "date_end":754704000000,
    "smoothed_cost_price":0.7900231956,
    "STORE":104,
    "UPC":7020211703
  },
  {
    "date_start":754790400000,
    "date_end":755308800000,
    "smoothed_cost_price":0.7900242509,
    "STORE":104,
    "UPC":7020211703
  },
  {
    "date_start":755395200000,
    "date_end":755913600000,
    "smoothed_cost_price":0.7900256599,
    "STORE":104,
    "UPC":7020211703
  },
  {
    "date_start":756000000000,
    "date_end":756518400000,
    "smoothed_cost_price":0.7900273581,
    "STORE":104,
    "UPC":7020211703
  },
  {
    "date_start":756604800000,
    "date_end":757123200000,
    "smoothed_cost_price":0.790029293,
    "STORE":104,
    "UPC":7020211703
  },
  {
    "date_start":757209600000,
    "date_end":757728000000,
    "smoothed_cost_price":0.7900314215,
    "STORE":104,
    "UPC":7020211703
  },
  {
    "date_start":757814400000,
    "date_end":758332800000,
    "smoothed_cost_price":0.7900337085,
    "STORE":104,
    "UPC":7020211703
  },
  {
    "date_start":758419200000,
    "date_end":758937600000,
    "smoothed_cost_price":0.7900361251,
    "STORE":104,
    "UPC":7020211703
  },
  {
    "date_start":759024000000,
    "date_end":759542400000,
    "smoothed_cost_price":0.7900386478,
    "STORE":104,
    "UPC":7020211703
  },
  {
    "date_start":759628800000,
    "date_end":760147200000,
    "smoothed_cost_price":0.7900412573,
    "STORE":104,
    "UPC":7020211703
  },
  {
    "date_start":760233600000,
    "date_end":760752000000,
    "smoothed_cost_price":0.7900373924,
    "STORE":104,
    "UPC":7020211703
  },
  {
    "date_start":760838400000,
    "date_end":761356800000,
    "smoothed_cost_price":0.7900342301,
    "STORE":104,
    "UPC":7020211703
  },
  {
    "date_start":761443200000,
    "date_end":761961600000,
    "smoothed_cost_price":0.7900316428,
    "STORE":104,
    "UPC":7020211703
  },
  {
    "date_start":762048000000,
    "date_end":762566400000,
    "smoothed_cost_price":0.7900295259,
    "STORE":104,
    "UPC":7020211703
  },
  {
    "date_start":762652800000,
    "date_end":763171200000,
    "smoothed_cost_price":0.790027794,
    "STORE":104,
    "UPC":7020211703
  },
  {
    "date_start":763257600000,
    "date_end":763776000000,
    "smoothed_cost_price":0.7900263769,
    "STORE":104,
    "UPC":7020211703
  },
  {
    "date_start":763862400000,
    "date_end":764380800000,
    "smoothed_cost_price":0.7900252174,
    "STORE":104,
    "UPC":7020211703
  },
  {
    "date_start":764467200000,
    "date_end":764985600000,
    "smoothed_cost_price":0.7900242688,
    "STORE":104,
    "UPC":7020211703
  },
  {
    "date_start":765072000000,
    "date_end":765590400000,
    "smoothed_cost_price":0.7900234927,
    "STORE":104,
    "UPC":7020211703
  },
  {
    "date_start":765676800000,
    "date_end":766195200000,
    "smoothed_cost_price":0.7900228576,
    "STORE":104,
    "UPC":7020211703
  },
  {
    "date_start":766281600000,
    "date_end":766800000000,
    "smoothed_cost_price":0.7900223381,
    "STORE":104,
    "UPC":7020211703
  },
  {
    "date_start":766886400000,
    "date_end":767404800000,
    "smoothed_cost_price":0.790021913,
    "STORE":104,
    "UPC":7020211703
  },
  {
    "date_start":767491200000,
    "date_end":768009600000,
    "smoothed_cost_price":0.7900215652,
    "STORE":104,
    "UPC":7020211703
  },
  {
    "date_start":768096000000,
    "date_end":768614400000,
    "smoothed_cost_price":0.7900212806,
    "STORE":104,
    "UPC":7020211703
  },
  {
    "date_start":768700800000,
    "date_end":769219200000,
    "smoothed_cost_price":0.7900270477,
    "STORE":104,
    "UPC":7020211703
  },
  {
    "date_start":769305600000,
    "date_end":769824000000,
    "smoothed_cost_price":0.7900302663,
    "STORE":104,
    "UPC":7020211703
  },
  {
    "date_start":769910400000,
    "date_end":770428800000,
    "smoothed_cost_price":0.7900313997,
    "STORE":104,
    "UPC":7020211703
  },
  {
    "date_start":770515200000,
    "date_end":771033600000,
    "smoothed_cost_price":0.7900308271,
    "STORE":104,
    "UPC":7020211703
  },
  {
    "date_start":771120000000,
    "date_end":771638400000,
    "smoothed_cost_price":0.7900288585,
    "STORE":104,
    "UPC":7020211703
  },
  {
    "date_start":771724800000,
    "date_end":772243200000,
    "smoothed_cost_price":0.7900272479,
    "STORE":104,
    "UPC":7020211703
  },
  {
    "date_start":772329600000,
    "date_end":772848000000,
    "smoothed_cost_price":0.7900259301,
    "STORE":104,
    "UPC":7020211703
  },
  {
    "date_start":772934400000,
    "date_end":773452800000,
    "smoothed_cost_price":0.7900248519,
    "STORE":104,
    "UPC":7020211703
  },
  {
    "date_start":773539200000,
    "date_end":774057600000,
    "smoothed_cost_price":0.7772979697,
    "STORE":104,
    "UPC":7020211703
  },
  {
    "date_start":774144000000,
    "date_end":774662400000,
    "smoothed_cost_price":0.7541590661,
    "STORE":104,
    "UPC":7020211703
  },
  {
    "date_start":779587200000,
    "date_end":780105600000,
    "smoothed_cost_price":0.7424992359,
    "STORE":104,
    "UPC":7020211703
  },
  {
    "date_start":780192000000,
    "date_end":780710400000,
    "smoothed_cost_price":0.7420493748,
    "STORE":104,
    "UPC":7020211703
  },
  {
    "date_start":780796800000,
    "date_end":781315200000,
    "smoothed_cost_price":0.7386513067,
    "STORE":104,
    "UPC":7020211703
  },
  {
    "date_start":781401600000,
    "date_end":781920000000,
    "smoothed_cost_price":0.7328410691,
    "STORE":104,
    "UPC":7020211703
  },
  {
    "date_start":782006400000,
    "date_end":782524800000,
    "smoothed_cost_price":0.7250572384,
    "STORE":104,
    "UPC":7020211703
  },
  {
    "date_start":782611200000,
    "date_end":783129600000,
    "smoothed_cost_price":0.7277786496,
    "STORE":104,
    "UPC":7020211703
  },
  {
    "date_start":783216000000,
    "date_end":783734400000,
    "smoothed_cost_price":0.7309142587,
    "STORE":104,
    "UPC":7020211703
  },
  {
    "date_start":783820800000,
    "date_end":784339200000,
    "smoothed_cost_price":0.7343887572,
    "STORE":104,
    "UPC":7020211703
  },
  {
    "date_start":784425600000,
    "date_end":784944000000,
    "smoothed_cost_price":0.7381405286,
    "STORE":104,
    "UPC":7020211703
  },
  {
    "date_start":785030400000,
    "date_end":785548800000,
    "smoothed_cost_price":0.7421191597,
    "STORE":104,
    "UPC":7020211703
  },
  {
    "date_start":785635200000,
    "date_end":786153600000,
    "smoothed_cost_price":0.7462834034,
    "STORE":104,
    "UPC":7020211703
  },
  {
    "date_start":786240000000,
    "date_end":786758400000,
    "smoothed_cost_price":0.7505995119,
    "STORE":104,
    "UPC":7020211703
  },
  {
    "date_start":786844800000,
    "date_end":787363200000,
    "smoothed_cost_price":0.7550398734,
    "STORE":104,
    "UPC":7020211703
  },
  {
    "date_start":787449600000,
    "date_end":787968000000,
    "smoothed_cost_price":0.7595818964,
    "STORE":104,
    "UPC":7020211703
  },
  {
    "date_start":788054400000,
    "date_end":788572800000,
    "smoothed_cost_price":0.764207097,
    "STORE":104,
    "UPC":7020211703
  },
  {
    "date_start":788659200000,
    "date_end":789177600000,
    "smoothed_cost_price":0.7689003521,
    "STORE":104,
    "UPC":7020211703
  },
  {
    "date_start":789264000000,
    "date_end":789782400000,
    "smoothed_cost_price":0.8679422881,
    "STORE":104,
    "UPC":7020211703
  },
  {
    "date_start":789868800000,
    "date_end":790387200000,
    "smoothed_cost_price":0.9701265994,
    "STORE":104,
    "UPC":7020211703
  },
  {
    "date_start":790473600000,
    "date_end":790992000000,
    "smoothed_cost_price":0.9955559449,
    "STORE":104,
    "UPC":7020211703
  },
  {
    "date_start":791078400000,
    "date_end":791596800000,
    "smoothed_cost_price":0.9581857731,
    "STORE":104,
    "UPC":7020211703
  },
  {
    "date_start":791683200000,
    "date_end":792201600000,
    "smoothed_cost_price":1.022812178,
    "STORE":104,
    "UPC":7020211703
  },
  {
    "date_start":792288000000,
    "date_end":792806400000,
    "smoothed_cost_price":1.0968383275,
    "STORE":104,
    "UPC":7020211703
  },
  {
    "date_start":792892800000,
    "date_end":793411200000,
    "smoothed_cost_price":1.041053177,
    "STORE":104,
    "UPC":7020211703
  },
  {
    "date_start":793497600000,
    "date_end":794016000000,
    "smoothed_cost_price":0.9954107812,
    "STORE":104,
    "UPC":7020211703
  },
  {
    "date_start":794102400000,
    "date_end":794620800000,
    "smoothed_cost_price":0.9580670028,
    "STORE":104,
    "UPC":7020211703
  },
  {
    "date_start":794707200000,
    "date_end":795225600000,
    "smoothed_cost_price":0.9275130023,
    "STORE":104,
    "UPC":7020211703
  },
  {
    "date_start":795312000000,
    "date_end":795830400000,
    "smoothed_cost_price":0.9025142746,
    "STORE":104,
    "UPC":7020211703
  },
  {
    "date_start":795916800000,
    "date_end":796435200000,
    "smoothed_cost_price":0.8820607701,
    "STORE":104,
    "UPC":7020211703
  },
  {
    "date_start":796521600000,
    "date_end":797040000000,
    "smoothed_cost_price":0.8653260846,
    "STORE":104,
    "UPC":7020211703
  },
  {
    "date_start":797126400000,
    "date_end":797644800000,
    "smoothed_cost_price":0.8477820693,
    "STORE":104,
    "UPC":7020211703
  },
  {
    "date_start":797731200000,
    "date_end":798249600000,
    "smoothed_cost_price":0.8300078748,
    "STORE":104,
    "UPC":7020211703
  },
  {
    "date_start":798336000000,
    "date_end":798854400000,
    "smoothed_cost_price":0.8215297158,
    "STORE":104,
    "UPC":7020211703
  },
  {
    "date_start":798940800000,
    "date_end":799459200000,
    "smoothed_cost_price":0.8158006766,
    "STORE":104,
    "UPC":7020211703
  },
  {
    "date_start":799545600000,
    "date_end":800064000000,
    "smoothed_cost_price":0.8093672808,
    "STORE":104,
    "UPC":7020211703
  },
  {
    "date_start":800150400000,
    "date_end":800668800000,
    "smoothed_cost_price":0.8038335934,
    "STORE":104,
    "UPC":7020211703
  },
  {
    "date_start":800755200000,
    "date_end":801273600000,
    "smoothed_cost_price":0.801322031,
    "STORE":104,
    "UPC":7020211703
  },
  {
    "date_start":801360000000,
    "date_end":801878400000,
    "smoothed_cost_price":0.7992671162,
    "STORE":104,
    "UPC":7020211703
  },
  {
    "date_start":801964800000,
    "date_end":802483200000,
    "smoothed_cost_price":0.8303098224,
    "STORE":104,
    "UPC":7020211703
  },
  {
    "date_start":802569600000,
    "date_end":803088000000,
    "smoothed_cost_price":0.8552611274,
    "STORE":104,
    "UPC":7020211703
  },
  {
    "date_start":803174400000,
    "date_end":803692800000,
    "smoothed_cost_price":0.8759681951,
    "STORE":104,
    "UPC":7020211703
  },
  {
    "date_start":803779200000,
    "date_end":804297600000,
    "smoothed_cost_price":0.8930652506,
    "STORE":104,
    "UPC":7020211703
  },
  {
    "date_start":804384000000,
    "date_end":804902400000,
    "smoothed_cost_price":0.9070537505,
    "STORE":104,
    "UPC":7020211703
  },
  {
    "date_start":804988800000,
    "date_end":805507200000,
    "smoothed_cost_price":0.9184988867,
    "STORE":104,
    "UPC":7020211703
  },
  {
    "date_start":805593600000,
    "date_end":806112000000,
    "smoothed_cost_price":0.9278630892,
    "STORE":104,
    "UPC":7020211703
  },
  {
    "date_start":806198400000,
    "date_end":806716800000,
    "smoothed_cost_price":0.9355247093,
    "STORE":104,
    "UPC":7020211703
  },
  {
    "date_start":806803200000,
    "date_end":807321600000,
    "smoothed_cost_price":0.9417933076,
    "STORE":104,
    "UPC":7020211703
  },
  {
    "date_start":807408000000,
    "date_end":807926400000,
    "smoothed_cost_price":0.9469221608,
    "STORE":104,
    "UPC":7020211703
  },
  {
    "date_start":808012800000,
    "date_end":808531200000,
    "smoothed_cost_price":0.9511184952,
    "STORE":104,
    "UPC":7020211703
  },
  {
    "date_start":808617600000,
    "date_end":809136000000,
    "smoothed_cost_price":0.9545518597,
    "STORE":104,
    "UPC":7020211703
  },
  {
    "date_start":809222400000,
    "date_end":809740800000,
    "smoothed_cost_price":0.9573609761,
    "STORE":104,
    "UPC":7020211703
  },
  {
    "date_start":809827200000,
    "date_end":810345600000,
    "smoothed_cost_price":0.9596593441,
    "STORE":104,
    "UPC":7020211703
  },
  {
    "date_start":810432000000,
    "date_end":810950400000,
    "smoothed_cost_price":0.961539827,
    "STORE":104,
    "UPC":7020211703
  },
  {
    "date_start":811036800000,
    "date_end":811555200000,
    "smoothed_cost_price":0.9630784039,
    "STORE":104,
    "UPC":7020211703
  },
  {
    "date_start":811641600000,
    "date_end":812160000000,
    "smoothed_cost_price":0.9643372396,
    "STORE":104,
    "UPC":7020211703
  },
  {
    "date_start":812246400000,
    "date_end":812764800000,
    "smoothed_cost_price":0.965367196,
    "STORE":104,
    "UPC":7020211703
  },
  {
    "date_start":812851200000,
    "date_end":813369600000,
    "smoothed_cost_price":0.9662098876,
    "STORE":104,
    "UPC":7020211703
  },
  {
    "date_start":813456000000,
    "date_end":813974400000,
    "smoothed_cost_price":0.9668993626,
    "STORE":104,
    "UPC":7020211703
  },
  {
    "date_start":814060800000,
    "date_end":814579200000,
    "smoothed_cost_price":0.9674634785,
    "STORE":104,
    "UPC":7020211703
  },
  {
    "date_start":814665600000,
    "date_end":815184000000,
    "smoothed_cost_price":0.9679250279,
    "STORE":104,
    "UPC":7020211703
  },
  {
    "date_start":815270400000,
    "date_end":815788800000,
    "smoothed_cost_price":0.9355786592,
    "STORE":104,
    "UPC":7020211703
  },
  {
    "date_start":815875200000,
    "date_end":816393600000,
    "smoothed_cost_price":0.9086443575,
    "STORE":104,
    "UPC":7020211703
  },
  {
    "date_start":816480000000,
    "date_end":816998400000,
    "smoothed_cost_price":0.8870784743,
    "STORE":104,
    "UPC":7020211703
  },
  {
    "date_start":817084800000,
    "date_end":817603200000,
    "smoothed_cost_price":0.8694352972,
    "STORE":104,
    "UPC":7020211703
  },
  {
    "date_start":817689600000,
    "date_end":818208000000,
    "smoothed_cost_price":0.8783888795,
    "STORE":104,
    "UPC":7020211703
  },
  {
    "date_start":818294400000,
    "date_end":818812800000,
    "smoothed_cost_price":0.8623218105,
    "STORE":104,
    "UPC":7020211703
  },
  {
    "date_start":818899200000,
    "date_end":819417600000,
    "smoothed_cost_price":0.849179845,
    "STORE":104,
    "UPC":7020211703
  },
  {
    "date_start":819504000000,
    "date_end":820022400000,
    "smoothed_cost_price":0.8547844186,
    "STORE":104,
    "UPC":7020211703
  },
  {
    "date_start":820108800000,
    "date_end":820627200000,
    "smoothed_cost_price":0.8430128879,
    "STORE":104,
    "UPC":7020211703
  },
  {
    "date_start":820713600000,
    "date_end":821232000000,
    "smoothed_cost_price":0.8661174538,
    "STORE":104,
    "UPC":7020211703
  },
  {
    "date_start":821318400000,
    "date_end":821836800000,
    "smoothed_cost_price":0.8836695531,
    "STORE":104,
    "UPC":7020211703
  },
  {
    "date_start":821923200000,
    "date_end":822441600000,
    "smoothed_cost_price":0.9661470889,
    "STORE":104,
    "UPC":7020211703
  },
  {
    "date_start":822528000000,
    "date_end":823046400000,
    "smoothed_cost_price":1.0504665273,
    "STORE":104,
    "UPC":7020211703
  },
  {
    "date_start":823132800000,
    "date_end":823651200000,
    "smoothed_cost_price":1.1194551587,
    "STORE":104,
    "UPC":7020211703
  },
  {
    "date_start":823737600000,
    "date_end":824256000000,
    "smoothed_cost_price":1.1759004026,
    "STORE":104,
    "UPC":7020211703
  },
  {
    "date_start":824342400000,
    "date_end":824860800000,
    "smoothed_cost_price":1.2220828748,
    "STORE":104,
    "UPC":7020211703
  },
  {
    "date_start":824947200000,
    "date_end":825465600000,
    "smoothed_cost_price":1.2587619885,
    "STORE":104,
    "UPC":7020211703
  },
  {
    "date_start":825552000000,
    "date_end":826070400000,
    "smoothed_cost_price":1.2898787179,
    "STORE":104,
    "UPC":7020211703
  },
  {
    "date_start":826156800000,
    "date_end":826675200000,
    "smoothed_cost_price":1.3153378601,
    "STORE":104,
    "UPC":7020211703
  },
  {
    "date_start":826761600000,
    "date_end":827280000000,
    "smoothed_cost_price":1.3361680673,
    "STORE":104,
    "UPC":7020211703
  },
  {
    "date_start":827366400000,
    "date_end":827884800000,
    "smoothed_cost_price":1.3532109642,
    "STORE":104,
    "UPC":7020211703
  },
  {
    "date_start":827971200000,
    "date_end":828489600000,
    "smoothed_cost_price":1.3671646071,
    "STORE":104,
    "UPC":7020211703
  },
  {
    "date_start":828576000000,
    "date_end":829094400000,
    "smoothed_cost_price":1.3785717694,
    "STORE":104,
    "UPC":7020211703
  },
  {
    "date_start":829180800000,
    "date_end":829699200000,
    "smoothed_cost_price":1.3879049022,
    "STORE":104,
    "UPC":7020211703
  },
  {
    "date_start":829785600000,
    "date_end":830304000000,
    "smoothed_cost_price":1.3955505564,
    "STORE":104,
    "UPC":7020211703
  },
  {
    "date_start":830390400000,
    "date_end":830908800000,
    "smoothed_cost_price":1.4018060916,
    "STORE":104,
    "UPC":7020211703
  },
  {
    "date_start":830995200000,
    "date_end":831513600000,
    "smoothed_cost_price":1.4069148022,
    "STORE":104,
    "UPC":7020211703
  },
  {
    "date_start":831600000000,
    "date_end":832118400000,
    "smoothed_cost_price":1.4100701109,
    "STORE":104,
    "UPC":7020211703
  },
  {
    "date_start":832204800000,
    "date_end":832723200000,
    "smoothed_cost_price":1.4136899089,
    "STORE":104,
    "UPC":7020211703
  },
  {
    "date_start":832809600000,
    "date_end":833328000000,
    "smoothed_cost_price":1.4166379255,
    "STORE":104,
    "UPC":7020211703
  },
  {
    "date_start":833414400000,
    "date_end":833932800000,
    "smoothed_cost_price":1.419049939,
    "STORE":104,
    "UPC":7020211703
  },
  {
    "date_start":834019200000,
    "date_end":834537600000,
    "smoothed_cost_price":1.4189917683,
    "STORE":104,
    "UPC":7020211703
  },
  {
    "date_start":834624000000,
    "date_end":835142400000,
    "smoothed_cost_price":1.4201778104,
    "STORE":104,
    "UPC":7020211703
  },
  {
    "date_start":835228800000,
    "date_end":835747200000,
    "smoothed_cost_price":1.4203563903,
    "STORE":104,
    "UPC":7020211703
  },
  {
    "date_start":835833600000,
    "date_end":836352000000,
    "smoothed_cost_price":1.4221017739,
    "STORE":104,
    "UPC":7020211703
  },
  {
    "date_start":836438400000,
    "date_end":836956800000,
    "smoothed_cost_price":1.422517815,
    "STORE":104,
    "UPC":7020211703
  },
  {
    "date_start":837043200000,
    "date_end":837561600000,
    "smoothed_cost_price":1.4238702123,
    "STORE":104,
    "UPC":7020211703
  },
  {
    "date_start":837648000000,
    "date_end":838166400000,
    "smoothed_cost_price":1.3413487191,
    "STORE":104,
    "UPC":7020211703
  },
  {
    "date_start":838252800000,
    "date_end":838771200000,
    "smoothed_cost_price":1.2738311338,
    "STORE":104,
    "UPC":7020211703
  },
  {
    "date_start":838857600000,
    "date_end":839376000000,
    "smoothed_cost_price":1.2185894731,
    "STORE":104,
    "UPC":7020211703
  },
  {
    "date_start":839462400000,
    "date_end":839980800000,
    "smoothed_cost_price":1.1733917508,
    "STORE":104,
    "UPC":7020211703
  },
  {
    "date_start":840067200000,
    "date_end":840585600000,
    "smoothed_cost_price":1.2200303415,
    "STORE":104,
    "UPC":7020211703
  },
  {
    "date_start":840672000000,
    "date_end":841190400000,
    "smoothed_cost_price":1.2581891885,
    "STORE":104,
    "UPC":7020211703
  },
  {
    "date_start":841276800000,
    "date_end":841795200000,
    "smoothed_cost_price":1.2894100633,
    "STORE":104,
    "UPC":7020211703
  },
  {
    "date_start":841881600000,
    "date_end":842400000000,
    "smoothed_cost_price":1.3149544155,
    "STORE":104,
    "UPC":7020211703
  },
  {
    "date_start":842486400000,
    "date_end":843004800000,
    "smoothed_cost_price":1.3342077945,
    "STORE":104,
    "UPC":7020211703
  },
  {
    "date_start":843091200000,
    "date_end":843609600000,
    "smoothed_cost_price":1.3503867409,
    "STORE":104,
    "UPC":7020211703
  },
  {
    "date_start":843696000000,
    "date_end":844214400000,
    "smoothed_cost_price":1.3648538789,
    "STORE":104,
    "UPC":7020211703
  },
  {
    "date_start":844300800000,
    "date_end":844819200000,
    "smoothed_cost_price":1.3766811737,
    "STORE":104,
    "UPC":7020211703
  },
  {
    "date_start":844905600000,
    "date_end":845424000000,
    "smoothed_cost_price":1.3863580512,
    "STORE":104,
    "UPC":7020211703
  },
  {
    "date_start":845510400000,
    "date_end":846028800000,
    "smoothed_cost_price":1.3942876782,
    "STORE":104,
    "UPC":7020211703
  },
  {
    "date_start":846115200000,
    "date_end":846633600000,
    "smoothed_cost_price":1.4000641004,
    "STORE":104,
    "UPC":7020211703
  },
  {
    "date_start":846720000000,
    "date_end":847238400000,
    "smoothed_cost_price":1.404790264,
    "STORE":104,
    "UPC":7020211703
  },
  {
    "date_start":847324800000,
    "date_end":847843200000,
    "smoothed_cost_price":1.4093674887,
    "STORE":104,
    "UPC":7020211703
  },
  {
    "date_start":847929600000,
    "date_end":848448000000,
    "smoothed_cost_price":1.4117388544,
    "STORE":104,
    "UPC":7020211703
  },
  {
    "date_start":848534400000,
    "date_end":849052800000,
    "smoothed_cost_price":1.4150776081,
    "STORE":104,
    "UPC":7020211703
  },
  {
    "date_start":849139200000,
    "date_end":849657600000,
    "smoothed_cost_price":1.4177733157,
    "STORE":104,
    "UPC":7020211703
  },
  {
    "date_start":849744000000,
    "date_end":850262400000,
    "smoothed_cost_price":1.4200148947,
    "STORE":104,
    "UPC":7020211703
  },
  {
    "date_start":850348800000,
    "date_end":850867200000,
    "smoothed_cost_price":1.4218489138,
    "STORE":104,
    "UPC":7020211703
  },
  {
    "date_start":850953600000,
    "date_end":851472000000,
    "smoothed_cost_price":1.4224632931,
    "STORE":104,
    "UPC":7020211703
  },
  {
    "date_start":851558400000,
    "date_end":852076800000,
    "smoothed_cost_price":1.4238272398,
    "STORE":104,
    "UPC":7020211703
  },
  {
    "date_start":852163200000,
    "date_end":852681600000,
    "smoothed_cost_price":1.4249442871,
    "STORE":104,
    "UPC":7020211703
  },
  {
    "date_start":852768000000,
    "date_end":853286400000,
    "smoothed_cost_price":1.4258820531,
    "STORE":104,
    "UPC":7020211703
  },
  {
    "date_start":853372800000,
    "date_end":853891200000,
    "smoothed_cost_price":1.3570527707,
    "STORE":104,
    "UPC":7020211703
  },
  {
    "date_start":853977600000,
    "date_end":854496000000,
    "smoothed_cost_price":1.2539660851,
    "STORE":104,
    "UPC":7020211703
  },
  {
    "date_start":854582400000,
    "date_end":855100800000,
    "smoothed_cost_price":1.2199973424,
    "STORE":104,
    "UPC":7020211703
  },
  {
    "date_start":855187200000,
    "date_end":855705600000,
    "smoothed_cost_price":1.1922047347,
    "STORE":104,
    "UPC":7020211703
  },
  {
    "date_start":855792000000,
    "date_end":856310400000,
    "smoothed_cost_price":1.149309692,
    "STORE":104,
    "UPC":7020211703
  },
  {
    "date_start":856396800000,
    "date_end":856915200000,
    "smoothed_cost_price":1.114213748,
    "STORE":104,
    "UPC":7020211703
  },
  {
    "date_start":857001600000,
    "date_end":857520000000,
    "smoothed_cost_price":1.055279612,
    "STORE":104,
    "UPC":7020211703
  },
  {
    "date_start":857606400000,
    "date_end":858124800000,
    "smoothed_cost_price":1.0574356826,
    "STORE":104,
    "UPC":7020211703
  },
  {
    "date_start":858211200000,
    "date_end":858729600000,
    "smoothed_cost_price":1.0591997403,
    "STORE":104,
    "UPC":7020211703
  },
  {
    "date_start":858816000000,
    "date_end":859334400000,
    "smoothed_cost_price":0.9506419693,
    "STORE":104,
    "UPC":7020211703
  },
  {
    "date_start":859420800000,
    "date_end":859939200000,
    "smoothed_cost_price":0.8555219749,
    "STORE":104,
    "UPC":7020211703
  },
  {
    "date_start":860025600000,
    "date_end":860544000000,
    "smoothed_cost_price":0.7776965249,
    "STORE":104,
    "UPC":7020211703
  },
  {
    "date_start":860630400000,
    "date_end":861148800000,
    "smoothed_cost_price":0.8303222477,
    "STORE":104,
    "UPC":7020211703
  },
  {
    "date_start":861235200000,
    "date_end":861753600000,
    "smoothed_cost_price":0.8715711117,
    "STORE":104,
    "UPC":7020211703
  },
  {
    "date_start":861840000000,
    "date_end":862358400000,
    "smoothed_cost_price":0.856747455,
    "STORE":104,
    "UPC":7020211703
  },
  {
    "date_start":862444800000,
    "date_end":862963200000,
    "smoothed_cost_price":0.8950002814,
    "STORE":104,
    "UPC":7020211703
  }
]